<?xml version="1.0" ?>
<?xml-stylesheet type="text/xsl" href="psplibdocdisplay.xsl" ?>
<PSPLIBDOC>
	<PRXFILES>
		<PRXFILE>
		<PRX>vsh/module/radioshack_plugin.prx</PRX>
		<PRXNAME>radioshack_plugin_module</PRXNAME>
		<LIBRARIES>
			<LIBRARY>
				<NAME>sceVshBridge</NAME>
				<FLAGS>0x40010011</FLAGS>
				<FUNCTIONS>
					<FUNCTION>
						<NID>0x01789C5B</NID>
						<NAME>sceVshBridge_01789C5B</NAME>
					</FUNCTION>
					<FUNCTION>
						<NID>0x2EB0812A</NID>
						<NAME>sceVshBridge_2EB0812A</NAME>
					</FUNCTION>
					<FUNCTION>
						<NID>0x448B089E</NID>
						<NAME>sceVshBridge_448B089E</NAME>
					</FUNCTION>
					<FUNCTION>
						<NID>0x5F74D1BB</NID>
						<NAME>sceVshBridge_5F74D1BB</NAME>
					</FUNCTION>
				</FUNCTIONS>
			</LIBRARY>
			<LIBRARY>
				<NAME>sceWlanDrv</NAME>
				<FLAGS>0x40010011</FLAGS>
				<FUNCTIONS>
					<FUNCTION>
						<NID>0xD7763699</NID>
						<NAME>sceWlanGetSwitchState</NAME>
					</FUNCTION>
				</FUNCTIONS>
			</LIBRARY>
			<LIBRARY>
				<NAME>sceNetApctl</NAME>
				<FLAGS>0x00090011</FLAGS>
				<FUNCTIONS>
					<FUNCTION>
						<NID>0x5DEAC81B</NID>
						<NAME>sceNetApctlGetState</NAME>
					</FUNCTION>
				</FUNCTIONS>
			</LIBRARY>
			<LIBRARY>
				<NAME>sceParseHttp</NAME>
				<FLAGS>0x00090011</FLAGS>
				<FUNCTIONS>
					<FUNCTION>
						<NID>0xAD7BFDEF</NID>
						<NAME>sceParseHttpResponseHeader</NAME>
					</FUNCTION>
				</FUNCTIONS>
			</LIBRARY>
			<LIBRARY>
				<NAME>sceParseUri</NAME>
				<FLAGS>0x00090011</FLAGS>
				<FUNCTIONS>
					<FUNCTION>
						<NID>0x568518C9</NID>
						<NAME>sceUriParse</NAME>
					</FUNCTION>
				</FUNCTIONS>
			</LIBRARY>
			<LIBRARY>
				<NAME>sceNetInet</NAME>
				<FLAGS>0x00090011</FLAGS>
				<FUNCTIONS>
					<FUNCTION>
						<NID>0xE30B8C19</NID>
						<NAME>sceNetInetInetPton</NAME>
					</FUNCTION>
				</FUNCTIONS>
			</LIBRARY>
			<LIBRARY>
				<NAME>sceNetResolver</NAME>
				<FLAGS>0x00090011</FLAGS>
				<FUNCTIONS>
					<FUNCTION>
						<NID>0x224C5F44</NID>
						<NAME>sceNetResolverStartNtoA</NAME>
					</FUNCTION>
					<FUNCTION>
						<NID>0x244172AF</NID>
						<NAME>sceNetResolverCreate</NAME>
					</FUNCTION>
					<FUNCTION>
						<NID>0x94523E09</NID>
						<NAME>sceNetResolverDelete</NAME>
					</FUNCTION>
				</FUNCTIONS>
			</LIBRARY>
			<LIBRARY>
				<NAME>sceRtc</NAME>
				<FLAGS>0x40010011</FLAGS>
				<FUNCTIONS>
					<FUNCTION>
						<NID>0xE7C27D1B</NID>
						<NAME>sceRtcGetCurrentClockLocalTime</NAME>
					</FUNCTION>
				</FUNCTIONS>
			</LIBRARY>
			<LIBRARY>
				<NAME>scePower</NAME>
				<FLAGS>0x40010011</FLAGS>
				<FUNCTIONS>
					<FUNCTION>
						<NID>0x87440F5E</NID>
						<NAME>scePowerIsPowerOnline</NAME>
					</FUNCTION>
					<FUNCTION>
						<NID>0xAC32C9CC</NID>
						<NAME>scePowerRequestSuspend</NAME>
					</FUNCTION>
					<FUNCTION>
						<NID>0xD3075926</NID>
						<NAME>scePowerIsLowBattery</NAME>
					</FUNCTION>
				</FUNCTIONS>
			</LIBRARY>
			<LIBRARY>
				<NAME>sceVshCommonGui</NAME>
				<FLAGS>0x00010011</FLAGS>
				<FUNCTIONS>
					<FUNCTION>
						<NID>0x0555C757</NID>
						<NAME>sceVshCommonGui_0555C757</NAME>
					</FUNCTION>
					<FUNCTION>
						<NID>0x15B33BDE</NID>
						<NAME>sceVshCommonGui_15B33BDE</NAME>
					</FUNCTION>
					<FUNCTION>
						<NID>0x25489D52</NID>
						<NAME>sceVshCommonGui_25489D52</NAME>
					</FUNCTION>
					<FUNCTION>
						<NID>0x38855541</NID>
						<NAME>sceVshCommonGui_38855541</NAME>
					</FUNCTION>
					<FUNCTION>
						<NID>0x3FA4619E</NID>
						<NAME>sceVshCommonGui_3FA4619E</NAME>
					</FUNCTION>
					<FUNCTION>
						<NID>0x565E9AE2</NID>
						<NAME>sceVshCommonGui_565E9AE2</NAME>
					</FUNCTION>
					<FUNCTION>
						<NID>0x5AFF4B9F</NID>
						<NAME>sceVshCommonGui_5AFF4B9F</NAME>
					</FUNCTION>
					<FUNCTION>
						<NID>0x6367CB49</NID>
						<NAME>sceVshCommonGui_6367CB49</NAME>
					</FUNCTION>
					<FUNCTION>
						<NID>0x69A07897</NID>
						<NAME>sceVshCommonGui_69A07897</NAME>
					</FUNCTION>
					<FUNCTION>
						<NID>0x6FE443F8</NID>
						<NAME>sceVshCommonGui_6FE443F8</NAME>
					</FUNCTION>
					<FUNCTION>
						<NID>0xA745DB12</NID>
						<NAME>sceVshCommonGui_A745DB12</NAME>
					</FUNCTION>
					<FUNCTION>
						<NID>0xB298063A</NID>
						<NAME>sceVshCommonGui_B298063A</NAME>
					</FUNCTION>
					<FUNCTION>
						<NID>0xB3B020CB</NID>
						<NAME>sceVshCommonGui_B3B020CB</NAME>
					</FUNCTION>
					<FUNCTION>
						<NID>0xB5EB251D</NID>
						<NAME>sceVshCommonGui_B5EB251D</NAME>
					</FUNCTION>
					<FUNCTION>
						<NID>0xC6B71F08</NID>
						<NAME>sceVshCommonGui_C6B71F08</NAME>
					</FUNCTION>
					<FUNCTION>
						<NID>0xDC4D90A3</NID>
						<NAME>sceVshCommonGui_DC4D90A3</NAME>
					</FUNCTION>
					<FUNCTION>
						<NID>0xEE1A71E9</NID>
						<NAME>sceVshCommonGui_EE1A71E9</NAME>
					</FUNCTION>
					<FUNCTION>
						<NID>0xF5471399</NID>
						<NAME>sceVshCommonGui_F5471399</NAME>
					</FUNCTION>
					<FUNCTION>
						<NID>0xFA85A7E1</NID>
						<NAME>sceVshCommonGui_FA85A7E1</NAME>
					</FUNCTION>
				</FUNCTIONS>
			</LIBRARY>
			<LIBRARY>
				<NAME>sceVshCommonUtil</NAME>
				<FLAGS>0x00010011</FLAGS>
				<FUNCTIONS>
					<FUNCTION>
						<NID>0xB3F4BEA8</NID>
						<NAME>sceVshCommonUtil_B3F4BEA8</NAME>
					</FUNCTION>
					<FUNCTION>
						<NID>0xB5C86FBB</NID>
						<NAME>sceVshCommonUtil_B5C86FBB</NAME>
					</FUNCTION>
					<FUNCTION>
						<NID>0xCFD3381F</NID>
						<NAME>sceVshCommonUtil_CFD3381F</NAME>
					</FUNCTION>
					<FUNCTION>
						<NID>0xEBA4F812</NID>
						<NAME>sceVshCommonUtil_EBA4F812</NAME>
					</FUNCTION>
				</FUNCTIONS>
			</LIBRARY>
			<LIBRARY>
				<NAME>vsh</NAME>
				<FLAGS>0x00010011</FLAGS>
				<FUNCTIONS>
					<FUNCTION>
						<NID>0x1B1CE2CF</NID>
						<NAME>vsh_1B1CE2CF</NAME>
					</FUNCTION>
					<FUNCTION>
						<NID>0x21871D45</NID>
						<NAME>vsh_21871D45</NAME>
					</FUNCTION>
					<FUNCTION>
						<NID>0x24467A2B</NID>
						<NAME>vsh_24467A2B</NAME>
					</FUNCTION>
					<FUNCTION>
						<NID>0x266BDCE1</NID>
						<NAME>vsh_266BDCE1</NAME>
					</FUNCTION>
					<FUNCTION>
						<NID>0x3EA6BEA3</NID>
						<NAME>vsh_3EA6BEA3</NAME>
					</FUNCTION>
					<FUNCTION>
						<NID>0xE261B0EE</NID>
						<NAME>vsh_E261B0EE</NAME>
					</FUNCTION>
				</FUNCTIONS>
			</LIBRARY>
			<LIBRARY>
				<NAME>scePaf</NAME>
				<FLAGS>0x00010011</FLAGS>
				<FUNCTIONS>
					<FUNCTION>
						<NID>0x0034216F</NID>
						<NAME>scePaf_0034216F</NAME>
					</FUNCTION>
					<FUNCTION>
						<NID>0x047C9996</NID>
						<NAME>scePaf_047C9996</NAME>
					</FUNCTION>
					<FUNCTION>
						<NID>0x07C50769</NID>
						<NAME>scePaf_07C50769</NAME>
					</FUNCTION>
					<FUNCTION>
						<NID>0x0897E275</NID>
						<NAME>scePaf_0897E275</NAME>
					</FUNCTION>
					<FUNCTION>
						<NID>0x0A6D0925</NID>
						<NAME>scePaf_0A6D0925</NAME>
					</FUNCTION>
					<FUNCTION>
						<NID>0x0CEA9245</NID>
						<NAME>scePaf_0CEA9245</NAME>
					</FUNCTION>
					<FUNCTION>
						<NID>0x1009FCA7</NID>
						<NAME>scePaf_1009FCA7</NAME>
					</FUNCTION>
					<FUNCTION>
						<NID>0x110673DB</NID>
						<NAME>scePaf_110673DB</NAME>
					</FUNCTION>
					<FUNCTION>
						<NID>0x1183E654</NID>
						<NAME>scePaf_1183E654</NAME>
					</FUNCTION>
					<FUNCTION>
						<NID>0x11EFC5FD</NID>
						<NAME>scePaf_11EFC5FD</NAME>
					</FUNCTION>
					<FUNCTION>
						<NID>0x11FA6015</NID>
						<NAME>scePaf_11FA6015</NAME>
					</FUNCTION>
					<FUNCTION>
						<NID>0x130A45DC</NID>
						<NAME>scePaf_130A45DC</NAME>
					</FUNCTION>
					<FUNCTION>
						<NID>0x156FBB30</NID>
						<NAME>scePaf_156FBB30</NAME>
					</FUNCTION>
					<FUNCTION>
						<NID>0x15AFC8D3</NID>
						<NAME>scePaf_15AFC8D3</NAME>
					</FUNCTION>
					<FUNCTION>
						<NID>0x1898BDB8</NID>
						<NAME>scePaf_1898BDB8</NAME>
					</FUNCTION>
					<FUNCTION>
						<NID>0x19624778</NID>
						<NAME>scePaf_19624778</NAME>
					</FUNCTION>
					<FUNCTION>
						<NID>0x1E2DDA60</NID>
						<NAME>scePaf_1E2DDA60</NAME>
					</FUNCTION>
					<FUNCTION>
						<NID>0x21EE8663</NID>
						<NAME>scePaf_21EE8663</NAME>
					</FUNCTION>
					<FUNCTION>
						<NID>0x22FB4177</NID>
						<NAME>scePaf_22FB4177</NAME>
					</FUNCTION>
					<FUNCTION>
						<NID>0x2338483F</NID>
						<NAME>scePaf_2338483F</NAME>
					</FUNCTION>
					<FUNCTION>
						<NID>0x25D4001A</NID>
						<NAME>scePaf_25D4001A</NAME>
					</FUNCTION>
					<FUNCTION>
						<NID>0x265053DF</NID>
						<NAME>scePaf_265053DF</NAME>
					</FUNCTION>
					<FUNCTION>
						<NID>0x2788491B</NID>
						<NAME>scePaf_2788491B</NAME>
					</FUNCTION>
					<FUNCTION>
						<NID>0x27F4E35C</NID>
						<NAME>scePaf_27F4E35C</NAME>
					</FUNCTION>
					<FUNCTION>
						<NID>0x2B7A3DA3</NID>
						<NAME>scePaf_2B7A3DA3</NAME>
					</FUNCTION>
					<FUNCTION>
						<NID>0x2CDC5A6E</NID>
						<NAME>scePaf_2CDC5A6E</NAME>
					</FUNCTION>
					<FUNCTION>
						<NID>0x2E6E65FA</NID>
						<NAME>scePaf_2E6E65FA</NAME>
					</FUNCTION>
					<FUNCTION>
						<NID>0x2FF405DB</NID>
						<NAME>scePaf_2FF405DB</NAME>
					</FUNCTION>
					<FUNCTION>
						<NID>0x30BCB0F4</NID>
						<NAME>scePaf_30BCB0F4</NAME>
					</FUNCTION>
					<FUNCTION>
						<NID>0x31AC0624</NID>
						<NAME>scePaf_31AC0624</NAME>
					</FUNCTION>
					<FUNCTION>
						<NID>0x323826CA</NID>
						<NAME>scePaf_323826CA</NAME>
					</FUNCTION>
					<FUNCTION>
						<NID>0x336E37F3</NID>
						<NAME>scePaf_336E37F3</NAME>
					</FUNCTION>
					<FUNCTION>
						<NID>0x3447707B</NID>
						<NAME>scePaf_3447707B</NAME>
					</FUNCTION>
					<FUNCTION>
						<NID>0x36C437F1</NID>
						<NAME>scePaf_36C437F1</NAME>
					</FUNCTION>
					<FUNCTION>
						<NID>0x3C8DD7F0</NID>
						<NAME>scePaf_3C8DD7F0</NAME>
					</FUNCTION>
					<FUNCTION>
						<NID>0x407C762E</NID>
						<NAME>scePaf_407C762E</NAME>
					</FUNCTION>
					<FUNCTION>
						<NID>0x4376CC55</NID>
						<NAME>scePaf_4376CC55</NAME>
					</FUNCTION>
					<FUNCTION>
						<NID>0x44653A84</NID>
						<NAME>scePaf_44653A84</NAME>
					</FUNCTION>
					<FUNCTION>
						<NID>0x4508F2FA</NID>
						<NAME>scePaf_4508F2FA</NAME>
					</FUNCTION>
					<FUNCTION>
						<NID>0x46B03301</NID>
						<NAME>scePaf_46B03301</NAME>
					</FUNCTION>
					<FUNCTION>
						<NID>0x485890F9</NID>
						<NAME>scePaf_485890F9</NAME>
					</FUNCTION>
					<FUNCTION>
						<NID>0x48BB05D5</NID>
						<NAME>scePaf_48BB05D5</NAME>
					</FUNCTION>
					<FUNCTION>
						<NID>0x4B7C764E</NID>
						<NAME>scePaf_4B7C764E</NAME>
					</FUNCTION>
					<FUNCTION>
						<NID>0x4C8173AE</NID>
						<NAME>scePaf_4C8173AE</NAME>
					</FUNCTION>
					<FUNCTION>
						<NID>0x4E87FDFC</NID>
						<NAME>scePaf_4E87FDFC</NAME>
					</FUNCTION>
					<FUNCTION>
						<NID>0x4FEF4DB9</NID>
						<NAME>scePaf_4FEF4DB9</NAME>
					</FUNCTION>
					<FUNCTION>
						<NID>0x531031AD</NID>
						<NAME>scePaf_531031AD</NAME>
					</FUNCTION>
					<FUNCTION>
						<NID>0x56833008</NID>
						<NAME>scePaf_56833008</NAME>
					</FUNCTION>
					<FUNCTION>
						<NID>0x5A693901</NID>
						<NAME>scePaf_5A693901</NAME>
					</FUNCTION>
					<FUNCTION>
						<NID>0x5AB3E9A8</NID>
						<NAME>scePaf_5AB3E9A8</NAME>
					</FUNCTION>
					<FUNCTION>
						<NID>0x5B4B2C1C</NID>
						<NAME>scePaf_5B4B2C1C</NAME>
					</FUNCTION>
					<FUNCTION>
						<NID>0x5C068AD6</NID>
						<NAME>scePaf_5C068AD6</NAME>
					</FUNCTION>
					<FUNCTION>
						<NID>0x5D2A7FC4</NID>
						<NAME>scePaf_5D2A7FC4</NAME>
					</FUNCTION>
					<FUNCTION>
						<NID>0x5DA73981</NID>
						<NAME>scePaf_5DA73981</NAME>
					</FUNCTION>
					<FUNCTION>
						<NID>0x5E00570F</NID>
						<NAME>scePaf_5E00570F</NAME>
					</FUNCTION>
					<FUNCTION>
						<NID>0x5E770EF9</NID>
						<NAME>scePaf_5E770EF9</NAME>
					</FUNCTION>
					<FUNCTION>
						<NID>0x60F871BB</NID>
						<NAME>scePaf_60F871BB</NAME>
					</FUNCTION>
					<FUNCTION>
						<NID>0x6439FDBC</NID>
						<NAME>scePaf_6439FDBC</NAME>
					</FUNCTION>
					<FUNCTION>
						<NID>0x64A8F0B9</NID>
						<NAME>scePaf_64A8F0B9</NAME>
					</FUNCTION>
					<FUNCTION>
						<NID>0x6690204E</NID>
						<NAME>scePaf_6690204E</NAME>
					</FUNCTION>
					<FUNCTION>
						<NID>0x676BAC3B</NID>
						<NAME>scePaf_676BAC3B</NAME>
					</FUNCTION>
					<FUNCTION>
						<NID>0x68CE0A83</NID>
						<NAME>scePaf_68CE0A83</NAME>
					</FUNCTION>
					<FUNCTION>
						<NID>0x6A1B3619</NID>
						<NAME>scePaf_6A1B3619</NAME>
					</FUNCTION>
					<FUNCTION>
						<NID>0x6BD7452C</NID>
						<NAME>scePaf_6BD7452C</NAME>
					</FUNCTION>
					<FUNCTION>
						<NID>0x6BEF472A</NID>
						<NAME>scePaf_6BEF472A</NAME>
					</FUNCTION>
					<FUNCTION>
						<NID>0x6CEA048C</NID>
						<NAME>scePaf_6CEA048C</NAME>
					</FUNCTION>
					<FUNCTION>
						<NID>0x6D03433C</NID>
						<NAME>scePaf_6D03433C</NAME>
					</FUNCTION>
					<FUNCTION>
						<NID>0x6E5AF076</NID>
						<NAME>scePaf_6E5AF076</NAME>
					</FUNCTION>
					<FUNCTION>
						<NID>0x711CD018</NID>
						<NAME>scePaf_711CD018</NAME>
					</FUNCTION>
					<FUNCTION>
						<NID>0x76528919</NID>
						<NAME>scePaf_76528919</NAME>
					</FUNCTION>
					<FUNCTION>
						<NID>0x767616E0</NID>
						<NAME>scePaf_767616E0</NAME>
					</FUNCTION>
					<FUNCTION>
						<NID>0x78E094C6</NID>
						<NAME>scePaf_78E094C6</NAME>
					</FUNCTION>
					<FUNCTION>
						<NID>0x79B2405B</NID>
						<NAME>scePaf_79B2405B</NAME>
					</FUNCTION>
					<FUNCTION>
						<NID>0x7A618FD3</NID>
						<NAME>scePaf_7A618FD3</NAME>
					</FUNCTION>
					<FUNCTION>
						<NID>0x7AFE0640</NID>
						<NAME>scePaf_7AFE0640</NAME>
					</FUNCTION>
					<FUNCTION>
						<NID>0x7B15E9DC</NID>
						<NAME>scePaf_7B15E9DC</NAME>
					</FUNCTION>
					<FUNCTION>
						<NID>0x84A46DD7</NID>
						<NAME>scePaf_84A46DD7</NAME>
					</FUNCTION>
					<FUNCTION>
						<NID>0x88A5E3CF</NID>
						<NAME>scePaf_88A5E3CF</NAME>
					</FUNCTION>
					<FUNCTION>
						<NID>0x904D869C</NID>
						<NAME>scePaf_904D869C</NAME>
					</FUNCTION>
					<FUNCTION>
						<NID>0x918CB54A</NID>
						<NAME>scePaf_918CB54A</NAME>
					</FUNCTION>
					<FUNCTION>
						<NID>0x91DEAA4D</NID>
						<NAME>scePaf_91DEAA4D</NAME>
					</FUNCTION>
					<FUNCTION>
						<NID>0x92A7C11B</NID>
						<NAME>scePaf_92A7C11B</NAME>
					</FUNCTION>
					<FUNCTION>
						<NID>0x937DE11C</NID>
						<NAME>scePaf_937DE11C</NAME>
					</FUNCTION>
					<FUNCTION>
						<NID>0x94E322DD</NID>
						<NAME>scePaf_94E322DD</NAME>
					</FUNCTION>
					<FUNCTION>
						<NID>0x967A56EF</NID>
						<NAME>scePaf_967A56EF</NAME>
					</FUNCTION>
					<FUNCTION>
						<NID>0x970DC20D</NID>
						<NAME>scePaf_970DC20D</NAME>
					</FUNCTION>
					<FUNCTION>
						<NID>0x98DE3BA6</NID>
						<NAME>scePaf_98DE3BA6</NAME>
					</FUNCTION>
					<FUNCTION>
						<NID>0x9E2F5F35</NID>
						<NAME>scePaf_9E2F5F35</NAME>
					</FUNCTION>
					<FUNCTION>
						<NID>0xA0E3AAE0</NID>
						<NAME>scePaf_A0E3AAE0</NAME>
					</FUNCTION>
					<FUNCTION>
						<NID>0xA1529507</NID>
						<NAME>scePaf_A1529507</NAME>
					</FUNCTION>
					<FUNCTION>
						<NID>0xA6810C75</NID>
						<NAME>scePaf_A6810C75</NAME>
					</FUNCTION>
					<FUNCTION>
						<NID>0xA78805B0</NID>
						<NAME>scePaf_A78805B0</NAME>
					</FUNCTION>
					<FUNCTION>
						<NID>0xA9FC7990</NID>
						<NAME>scePaf_A9FC7990</NAME>
					</FUNCTION>
					<FUNCTION>
						<NID>0xAB9A6186</NID>
						<NAME>scePaf_AB9A6186</NAME>
					</FUNCTION>
					<FUNCTION>
						<NID>0xACB55E4C</NID>
						<NAME>scePaf_ACB55E4C</NAME>
					</FUNCTION>
					<FUNCTION>
						<NID>0xAF8BAECD</NID>
						<NAME>scePaf_AF8BAECD</NAME>
					</FUNCTION>
					<FUNCTION>
						<NID>0xB117860A</NID>
						<NAME>scePaf_B117860A</NAME>
					</FUNCTION>
					<FUNCTION>
						<NID>0xB8853D5C</NID>
						<NAME>scePaf_B8853D5C</NAME>
					</FUNCTION>
					<FUNCTION>
						<NID>0xBD500444</NID>
						<NAME>scePaf_BD500444</NAME>
					</FUNCTION>
					<FUNCTION>
						<NID>0xBEF0C05C</NID>
						<NAME>scePaf_BEF0C05C</NAME>
					</FUNCTION>
					<FUNCTION>
						<NID>0xBFC95DA3</NID>
						<NAME>scePaf_BFC95DA3</NAME>
					</FUNCTION>
					<FUNCTION>
						<NID>0xC35FF2A3</NID>
						<NAME>scePaf_C35FF2A3</NAME>
					</FUNCTION>
					<FUNCTION>
						<NID>0xCA38E212</NID>
						<NAME>scePaf_CA38E212</NAME>
					</FUNCTION>
					<FUNCTION>
						<NID>0xCC775AC2</NID>
						<NAME>scePaf_CC775AC2</NAME>
					</FUNCTION>
					<FUNCTION>
						<NID>0xD1465051</NID>
						<NAME>scePaf_D1465051</NAME>
					</FUNCTION>
					<FUNCTION>
						<NID>0xD27A723F</NID>
						<NAME>scePaf_D27A723F</NAME>
					</FUNCTION>
					<FUNCTION>
						<NID>0xD2AF9730</NID>
						<NAME>scePaf_D2AF9730</NAME>
					</FUNCTION>
					<FUNCTION>
						<NID>0xD3621360</NID>
						<NAME>scePaf_D3621360</NAME>
					</FUNCTION>
					<FUNCTION>
						<NID>0xD51C1B20</NID>
						<NAME>scePaf_D51C1B20</NAME>
					</FUNCTION>
					<FUNCTION>
						<NID>0xD59E54BC</NID>
						<NAME>scePaf_D59E54BC</NAME>
					</FUNCTION>
					<FUNCTION>
						<NID>0xD86C4533</NID>
						<NAME>scePaf_D86C4533</NAME>
					</FUNCTION>
					<FUNCTION>
						<NID>0xDE0E0F8B</NID>
						<NAME>scePaf_DE0E0F8B</NAME>
					</FUNCTION>
					<FUNCTION>
						<NID>0xE305A594</NID>
						<NAME>scePaf_E305A594</NAME>
					</FUNCTION>
					<FUNCTION>
						<NID>0xE3D530AE</NID>
						<NAME>scePaf_E3D530AE</NAME>
					</FUNCTION>
					<FUNCTION>
						<NID>0xE41E36CA</NID>
						<NAME>scePaf_E41E36CA</NAME>
					</FUNCTION>
					<FUNCTION>
						<NID>0xE487AEFA</NID>
						<NAME>scePaf_E487AEFA</NAME>
					</FUNCTION>
					<FUNCTION>
						<NID>0xE5F2B62F</NID>
						<NAME>scePaf_E5F2B62F</NAME>
					</FUNCTION>
					<FUNCTION>
						<NID>0xE69238D0</NID>
						<NAME>scePaf_E69238D0</NAME>
					</FUNCTION>
					<FUNCTION>
						<NID>0xE8805459</NID>
						<NAME>scePaf_E8805459</NAME>
					</FUNCTION>
					<FUNCTION>
						<NID>0xE88F8E4E</NID>
						<NAME>scePaf_E88F8E4E</NAME>
					</FUNCTION>
					<FUNCTION>
						<NID>0xE8CCC611</NID>
						<NAME>scePaf_E8CCC611</NAME>
					</FUNCTION>
					<FUNCTION>
						<NID>0xE947F1B6</NID>
						<NAME>scePaf_E947F1B6</NAME>
					</FUNCTION>
					<FUNCTION>
						<NID>0xEBF1BC9F</NID>
						<NAME>scePaf_EBF1BC9F</NAME>
					</FUNCTION>
					<FUNCTION>
						<NID>0xED055C3C</NID>
						<NAME>scePaf_ED055C3C</NAME>
					</FUNCTION>
					<FUNCTION>
						<NID>0xED355845</NID>
						<NAME>scePaf_ED355845</NAME>
					</FUNCTION>
					<FUNCTION>
						<NID>0xEDF5A271</NID>
						<NAME>scePaf_EDF5A271</NAME>
					</FUNCTION>
					<FUNCTION>
						<NID>0xEE9BD6A9</NID>
						<NAME>scePaf_EE9BD6A9</NAME>
					</FUNCTION>
					<FUNCTION>
						<NID>0xF0691DEB</NID>
						<NAME>scePaf_F0691DEB</NAME>
					</FUNCTION>
					<FUNCTION>
						<NID>0xF1F9D49A</NID>
						<NAME>scePaf_F1F9D49A</NAME>
					</FUNCTION>
					<FUNCTION>
						<NID>0xF3810B20</NID>
						<NAME>scePaf_F3810B20</NAME>
					</FUNCTION>
					<FUNCTION>
						<NID>0xF787B3B0</NID>
						<NAME>scePaf_F787B3B0</NAME>
					</FUNCTION>
					<FUNCTION>
						<NID>0xF9083964</NID>
						<NAME>scePaf_F9083964</NAME>
					</FUNCTION>
					<FUNCTION>
						<NID>0xFC3E5FB7</NID>
						<NAME>scePaf_FC3E5FB7</NAME>
					</FUNCTION>
					<FUNCTION>
						<NID>0xFFD71622</NID>
						<NAME>scePaf_FFD71622</NAME>
					</FUNCTION>
				</FUNCTIONS>
				<VARIABLES>
					<VARIABLE>
						<NID>0x724027B9</NID>
						<NAME>scePaf_724027B9</NAME>
					</VARIABLE>
					<VARIABLE>
						<NID>0x7BBB200B</NID>
						<NAME>scePaf_7BBB200B</NAME>
					</VARIABLE>
					<VARIABLE>
						<NID>0xCA6EB2BF</NID>
						<NAME>scePaf_CA6EB2BF</NAME>
					</VARIABLE>
				</VARIABLES>
			</LIBRARY>
			<LIBRARY>
				<NAME>sceHttp</NAME>
				<FLAGS>0x00090011</FLAGS>
				<FUNCTIONS>
					<FUNCTION>
						<NID>0x0282A3BD</NID>
						<NAME>sceHttpGetContentLength</NAME>
					</FUNCTION>
					<FUNCTION>
						<NID>0x03D9526F</NID>
						<NAME>sceHttpSetResolveRetry</NAME>
					</FUNCTION>
					<FUNCTION>
						<NID>0x0809C831</NID>
						<NAME>sceHttpEnableRedirect</NAME>
					</FUNCTION>
					<FUNCTION>
						<NID>0x0B12ABFB</NID>
						<NAME>sceHttpDisableCookie</NAME>
					</FUNCTION>
					<FUNCTION>
						<NID>0x1F0FC3E3</NID>
						<NAME>sceHttpSetRecvTimeOut</NAME>
					</FUNCTION>
					<FUNCTION>
						<NID>0x3EABA285</NID>
						<NAME>sceHttpAddExtraHeader</NAME>
					</FUNCTION>
					<FUNCTION>
						<NID>0x47940436</NID>
						<NAME>sceHttpSetResolveTimeOut</NAME>
					</FUNCTION>
					<FUNCTION>
						<NID>0x4CC7D78F</NID>
						<NAME>sceHttpGetStatusCode</NAME>
					</FUNCTION>
					<FUNCTION>
						<NID>0x5152773B</NID>
						<NAME>sceHttpDeleteConnection</NAME>
					</FUNCTION>
					<FUNCTION>
						<NID>0x8ACD1F73</NID>
						<NAME>sceHttpSetConnectTimeOut</NAME>
					</FUNCTION>
					<FUNCTION>
						<NID>0x9988172D</NID>
						<NAME>sceHttpSetSendTimeOut</NAME>
					</FUNCTION>
					<FUNCTION>
						<NID>0x9B1F1F36</NID>
						<NAME>sceHttpCreateTemplate</NAME>
					</FUNCTION>
					<FUNCTION>
						<NID>0xA5512E01</NID>
						<NAME>sceHttpDeleteRequest</NAME>
					</FUNCTION>
					<FUNCTION>
						<NID>0xAE948FEE</NID>
						<NAME>sceHttpDisableAuth</NAME>
					</FUNCTION>
					<FUNCTION>
						<NID>0xB509B09E</NID>
						<NAME>sceHttpCreateRequestWithURL</NAME>
					</FUNCTION>
					<FUNCTION>
						<NID>0xBB70706F</NID>
						<NAME>sceHttpSendRequest</NAME>
					</FUNCTION>
					<FUNCTION>
						<NID>0xC10B6BD9</NID>
						<NAME>sceHttpAbortRequest</NAME>
					</FUNCTION>
					<FUNCTION>
						<NID>0xCDF8ECB9</NID>
						<NAME>sceHttpCreateConnectionWithURL</NAME>
					</FUNCTION>
					<FUNCTION>
						<NID>0xD081EC8F</NID>
						<NAME>sceHttpGetNetworkErrno</NAME>
					</FUNCTION>
					<FUNCTION>
						<NID>0xD80BE761</NID>
						<NAME>sceHttp_D80BE761</NAME>
					</FUNCTION>
					<FUNCTION>
						<NID>0xDB266CCF</NID>
						<NAME>sceHttpGetAllHeader</NAME>
					</FUNCTION>
					<FUNCTION>
						<NID>0xEDEEB999</NID>
						<NAME>sceHttpReadData</NAME>
					</FUNCTION>
					<FUNCTION>
						<NID>0xFCF8C055</NID>
						<NAME>sceHttpDeleteTemplate</NAME>
					</FUNCTION>
				</FUNCTIONS>
			</LIBRARY>
			<LIBRARY>
				<NAME>sceAudiocodec</NAME>
				<FLAGS>0x40090011</FLAGS>
				<FUNCTIONS>
					<FUNCTION>
						<NID>0x29681260</NID>
						<NAME>sceAudiocodecReleaseEDRAM</NAME>
					</FUNCTION>
					<FUNCTION>
						<NID>0x3A20A200</NID>
						<NAME>sceAudiocodecGetEDRAM</NAME>
					</FUNCTION>
					<FUNCTION>
						<NID>0x59176A0F</NID>
						<NAME>sceAudiocodec_59176A0F</NAME>
					</FUNCTION>
					<FUNCTION>
						<NID>0x5B37EB1D</NID>
						<NAME>sceAudiocodecInit</NAME>
					</FUNCTION>
					<FUNCTION>
						<NID>0x70A703F8</NID>
						<NAME>sceAudiocodecDecode</NAME>
					</FUNCTION>
					<FUNCTION>
						<NID>0x8ACA11D5</NID>
						<NAME>sceAudiocodecGetInfo</NAME>
					</FUNCTION>
					<FUNCTION>
						<NID>0x9D3F790C</NID>
						<NAME>sceAudiocodecCheckNeedMem</NAME>
					</FUNCTION>
				</FUNCTIONS>
			</LIBRARY>
			<LIBRARY>
				<NAME>IoFileMgrForUser</NAME>
				<FLAGS>0x40010011</FLAGS>
				<FUNCTIONS>
					<FUNCTION>
						<NID>0x54F5FB11</NID>
						<NAME>sceIoDevctl</NAME>
					</FUNCTION>
					<FUNCTION>
						<NID>0x63632449</NID>
						<NAME>sceIoIoctl</NAME>
					</FUNCTION>
					<FUNCTION>
						<NID>0x6A638D83</NID>
						<NAME>sceIoRead</NAME>
					</FUNCTION>
					<FUNCTION>
						<NID>0x810C4BC3</NID>
						<NAME>sceIoClose</NAME>
					</FUNCTION>
					<FUNCTION>
						<NID>0x06A70004</NID>
						<NAME>sceIoMkdir</NAME>
					</FUNCTION>
					<FUNCTION>
						<NID>0xACE946E8</NID>
						<NAME>sceIoGetstat</NAME>
					</FUNCTION>
					<FUNCTION>
						<NID>0xB29DDF9C</NID>
						<NAME>sceIoDopen</NAME>
					</FUNCTION>
					<FUNCTION>
						<NID>0xB8A740F4</NID>
						<NAME>sceIoChstat</NAME>
					</FUNCTION>
					<FUNCTION>
						<NID>0xE3EB004C</NID>
						<NAME>sceIoDread</NAME>
					</FUNCTION>
					<FUNCTION>
						<NID>0xEB092469</NID>
						<NAME>sceIoDclose</NAME>
					</FUNCTION>
					<FUNCTION>
						<NID>0xF27A9C51</NID>
						<NAME>sceIoRemove</NAME>
					</FUNCTION>
					<FUNCTION>
						<NID>0x109F50BC</NID>
						<NAME>sceIoOpen</NAME>
					</FUNCTION>
				</FUNCTIONS>
			</LIBRARY>
			<LIBRARY>
				<NAME>sceSuspendForUser</NAME>
				<FLAGS>0x40000011</FLAGS>
				<FUNCTIONS>
					<FUNCTION>
						<NID>0x090CCB3F</NID>
						<NAME>sceKernelPowerTick</NAME>
					</FUNCTION>
					<FUNCTION>
						<NID>0x3AEE7261</NID>
						<NAME>sceKernelPowerUnlock</NAME>
					</FUNCTION>
					<FUNCTION>
						<NID>0xEADB1BD7</NID>
						<NAME>sceKernelPowerLock</NAME>
					</FUNCTION>
				</FUNCTIONS>
			</LIBRARY>
			<LIBRARY>
				<NAME>ThreadManForUser</NAME>
				<FLAGS>0x40010011</FLAGS>
				<FUNCTIONS>
					<FUNCTION>
						<NID>0xCEADEB47</NID>
						<NAME>sceKernelDelayThread</NAME>
					</FUNCTION>
					<FUNCTION>
						<NID>0xD6DA4BA1</NID>
						<NAME>sceKernelCreateSema</NAME>
					</FUNCTION>
					<FUNCTION>
						<NID>0xDB738F35</NID>
						<NAME>sceKernelGetSystemTime</NAME>
					</FUNCTION>
					<FUNCTION>
						<NID>0xEF9E4C70</NID>
						<NAME>sceKernelDeleteEventFlag</NAME>
					</FUNCTION>
					<FUNCTION>
						<NID>0xF475845D</NID>
						<NAME>sceKernelStartThread</NAME>
					</FUNCTION>
					<FUNCTION>
						<NID>0x1FB15A32</NID>
						<NAME>sceKernelSetEventFlag</NAME>
					</FUNCTION>
					<FUNCTION>
						<NID>0xF8170FBE</NID>
						<NAME>sceKernelDeleteMutex</NAME>
					</FUNCTION>
					<FUNCTION>
						<NID>0x278C0DF5</NID>
						<NAME>sceKernelWaitThreadEnd</NAME>
					</FUNCTION>
					<FUNCTION>
						<NID>0x28B6489C</NID>
						<NAME>sceKernelDeleteSema</NAME>
					</FUNCTION>
					<FUNCTION>
						<NID>0x293B45B8</NID>
						<NAME>sceKernelGetThreadId</NAME>
					</FUNCTION>
					<FUNCTION>
						<NID>0x30FD48F0</NID>
						<NAME>sceKernelPollEventFlag</NAME>
					</FUNCTION>
					<FUNCTION>
						<NID>0x3F53E640</NID>
						<NAME>sceKernelSignalSema</NAME>
					</FUNCTION>
					<FUNCTION>
						<NID>0x402FCF22</NID>
						<NAME>sceKernelWaitEventFlag</NAME>
					</FUNCTION>
					<FUNCTION>
						<NID>0x446D8DE6</NID>
						<NAME>sceKernelCreateThread</NAME>
					</FUNCTION>
					<FUNCTION>
						<NID>0x4E3A1105</NID>
						<NAME>sceKernelWaitSema</NAME>
					</FUNCTION>
					<FUNCTION>
						<NID>0x55C20A00</NID>
						<NAME>sceKernelCreateEventFlag</NAME>
					</FUNCTION>
					<FUNCTION>
						<NID>0x6652B8CA</NID>
						<NAME>sceKernelSetAlarm</NAME>
					</FUNCTION>
					<FUNCTION>
						<NID>0x6B30100F</NID>
						<NAME>sceKernelUnlockMutex</NAME>
					</FUNCTION>
					<FUNCTION>
						<NID>0x7E65B999</NID>
						<NAME>sceKernelCancelAlarm</NAME>
					</FUNCTION>
					<FUNCTION>
						<NID>0x812346E4</NID>
						<NAME>sceKernelClearEventFlag</NAME>
					</FUNCTION>
					<FUNCTION>
						<NID>0x9FA03CD3</NID>
						<NAME>sceKernelDeleteThread</NAME>
					</FUNCTION>
					<FUNCTION>
						<NID>0xAA73C935</NID>
						<NAME>sceKernelExitThread</NAME>
					</FUNCTION>
					<FUNCTION>
						<NID>0xB011B11F</NID>
						<NAME>sceKernelLockMutex</NAME>
					</FUNCTION>
					<FUNCTION>
						<NID>0xB7D098C6</NID>
						<NAME>sceKernelCreateMutex</NAME>
					</FUNCTION>
				</FUNCTIONS>
			</LIBRARY>
			<LIBRARY>
				<NAME>UtilsForUser</NAME>
				<FLAGS>0x40010011</FLAGS>
				<FUNCTIONS>
					<FUNCTION>
						<NID>0x79D1C3FA</NID>
						<NAME>sceKernelDcacheWritebackAll</NAME>
					</FUNCTION>
				</FUNCTIONS>
			</LIBRARY>
		</LIBRARIES>
		</PRXFILE>
	</PRXFILES>
</PSPLIBDOC>
