<?xml version="1.0" ?>
<?xml-stylesheet type="text/xsl" href="psplibdocdisplay.xsl" ?>
<PSPLIBDOC>
	<PRXFILES>
		<PRXFILE>
		<PRX>kd/ata.prx</PRX>
		<PRXNAME>sceATA_ATAPI_driver</PRXNAME>
		<LIBRARIES>
			<LIBRARY>
				<NAME>InterruptManagerForKernel</NAME>
				<FLAGS>0x00090011</FLAGS>
				<FUNCTIONS>
					<FUNCTION>
						<NID>0x092968F4</NID>
						<NAME>sceKernelCpuSuspendIntr</NAME>
					</FUNCTION>
					<FUNCTION>
						<NID>0x5F10D406</NID>
						<NAME>sceKernelCpuResumeIntr</NAME>
					</FUNCTION>
				</FUNCTIONS>
			</LIBRARY>
			<LIBRARY>
				<NAME>ThreadManForKernel</NAME>
				<FLAGS>0x00010011</FLAGS>
				<FUNCTIONS>
					<FUNCTION>
						<NID>0x6652B8CA</NID>
						<NAME>sceKernelSetAlarm</NAME>
					</FUNCTION>
					<FUNCTION>
						<NID>0x7E65B999</NID>
						<NAME>sceKernelCancelAlarm</NAME>
					</FUNCTION>
					<FUNCTION>
						<NID>0xCEADEB47</NID>
						<NAME>sceKernelDelayThread</NAME>
					</FUNCTION>
				</FUNCTIONS>
			</LIBRARY>
			<LIBRARY>
				<NAME>KDebugForKernel</NAME>
				<FLAGS>0x00010011</FLAGS>
				<FUNCTIONS>
					<FUNCTION>
						<NID>0x24C32559</NID>
						<NAME>KDebugForKernel_24C32559</NAME>
					</FUNCTION>
					<FUNCTION>
						<NID>0x84F370BC</NID>
						<NAME>Kprintf</NAME>
					</FUNCTION>
				</FUNCTIONS>
			</LIBRARY>
			<LIBRARY>
				<NAME>sceSysreg_driver</NAME>
				<FLAGS>0x00010011</FLAGS>
				<FUNCTIONS>
					<FUNCTION>
						<NID>0x0282ABDA</NID>
						<NAME>sceSysreg_driver_0282ABDA</NAME>
					</FUNCTION>
					<FUNCTION>
						<NID>0x0A81EC00</NID>
						<NAME>sceSysreg_driver_0A81EC00</NAME>
					</FUNCTION>
					<FUNCTION>
						<NID>0x16909002</NID>
						<NAME>sceSysregAtaBusClockEnable</NAME>
					</FUNCTION>
					<FUNCTION>
						<NID>0x1CF0A423</NID>
						<NAME>sceSysreg_driver_1CF0A423</NAME>
					</FUNCTION>
					<FUNCTION>
						<NID>0x520D0CDF</NID>
						<NAME>sceSysreg_driver_520D0CDF</NAME>
					</FUNCTION>
					<FUNCTION>
						<NID>0x52C2FD56</NID>
						<NAME>sceSysreg_driver_52C2FD56</NAME>
					</FUNCTION>
					<FUNCTION>
						<NID>0x7949C336</NID>
						<NAME>sceSysreg_driver_7949C336</NAME>
					</FUNCTION>
					<FUNCTION>
						<NID>0xB6C10DF0</NID>
						<NAME>sceSysregAtaBusClockDisable</NAME>
					</FUNCTION>
					<FUNCTION>
						<NID>0xD96AED94</NID>
						<NAME>sceSysreg_driver_D96AED94</NAME>
					</FUNCTION>
				</FUNCTIONS>
			</LIBRARY>
		</LIBRARIES>
		</PRXFILE>
	</PRXFILES>
</PSPLIBDOC>
