<?xml version="1.0" ?>
<?xml-stylesheet type="text/xsl" href="psplibdocdisplay.xsl" ?>
<PSPLIBDOC>
	<PRXFILES>
		<PRXFILE>
		<PRX>kd/pspnet_apctl.prx</PRX>
		<PRXNAME>sceNetApctl_Library</PRXNAME>
		<LIBRARIES>
			<LIBRARY>
				<NAME>sceNetApctl</NAME>
				<FLAGS>0x00010000</FLAGS>
				<FUNCTIONS>
					<FUNCTION>
						<NID>0xE2F91F9B</NID>
						<NAME>sceNetApctlInit</NAME>
					</FUNCTION>
					<FUNCTION>
						<NID>0xB3EDD0EC</NID>
						<NAME>sceNetApctlTerm</NAME>
					</FUNCTION>
					<FUNCTION>
						<NID>0x2BEFDF23</NID>
						<NAME>sceNetApctlGetInfo</NAME>
					</FUNCTION>
					<FUNCTION>
						<NID>0x8ABADD51</NID>
						<NAME>sceNetApctlAddHandler</NAME>
					</FUNCTION>
					<FUNCTION>
						<NID>0x5963991B</NID>
						<NAME>sceNetApctlDelHandler</NAME>
					</FUNCTION>
					<FUNCTION>
						<NID>0xCFB957C6</NID>
						<NAME>sceNetApctlConnect</NAME>
					</FUNCTION>
					<FUNCTION>
						<NID>0x24FE91A1</NID>
						<NAME>sceNetApctlDisconnect</NAME>
					</FUNCTION>
					<FUNCTION>
						<NID>0x5DEAC81B</NID>
						<NAME>sceNetApctlGetState</NAME>
					</FUNCTION>
				</FUNCTIONS>
			</LIBRARY>
			<LIBRARY>
				<NAME>sceNetApctl_lib</NAME>
				<FLAGS>0x00010000</FLAGS>
				<FUNCTIONS>
					<FUNCTION>
						<NID>0xB3CF6849</NID>
						<NAME>sceNetApctlScan</NAME>
					</FUNCTION>
					<FUNCTION>
						<NID>0x0C7FFA5C</NID>
						<NAME>sceNetApctl_lib_0C7FFA5C</NAME>
					</FUNCTION>
					<FUNCTION>
						<NID>0x96BEB231</NID>
						<NAME>sceNetApctl_lib_96BEB231</NAME>
					</FUNCTION>
					<FUNCTION>
						<NID>0x7CFAB990</NID>
						<NAME>sceNetApctl_lib_7CFAB990</NAME>
					</FUNCTION>
					<FUNCTION>
						<NID>0xE11BAFAB</NID>
						<NAME>sceNetApctl_lib_E11BAFAB</NAME>
					</FUNCTION>
				</FUNCTIONS>
			</LIBRARY>
			<LIBRARY>
				<NAME>sceNetApctl_internal_user</NAME>
				<FLAGS>0x00010000</FLAGS>
				<FUNCTIONS>
					<FUNCTION>
						<NID>0xE9B2E5E6</NID>
						<NAME>sceNetApctlScanUser</NAME>
					</FUNCTION>
					<FUNCTION>
						<NID>0x6BDDCB8C</NID>
						<NAME>sceNetApctl_internal_user_6BDDCB8C</NAME>
					</FUNCTION>
					<FUNCTION>
						<NID>0x04776994</NID>
						<NAME>sceNetApctl_internal_user_04776994</NAME>
					</FUNCTION>
				</FUNCTIONS>
			</LIBRARY>
		</LIBRARIES>
		</PRXFILE>
	</PRXFILES>
</PSPLIBDOC>
