<?xml version="1.0" ?>
<?xml-stylesheet type="text/xsl" href="psplibdocdisplay.xsl" ?>
<PSPLIBDOC>
	<PRXFILES>
		<PRXFILE>
		<PRX>kd/ge.prx</PRX>
		<PRXNAME>sceGE_Manager</PRXNAME>
		<LIBRARIES>
			<LIBRARY>
				<NAME>sceGe_driver</NAME>
				<FLAGS>0x00010011</FLAGS>
				<FUNCTIONS>
					<FUNCTION>
						<NID>0x03F307B3</NID>
						<NAME>sceGe_driver_03F307B3</NAME>
					</FUNCTION>
					<FUNCTION>
						<NID>0x06A873EF</NID>
						<NAME>sceGe_driver_06A873EF</NAME>
					</FUNCTION>
					<FUNCTION>
						<NID>0x0832D7DA</NID>
						<NAME>sceGe_driver_0832D7DA</NAME>
					</FUNCTION>
					<FUNCTION>
						<NID>0x1A6BBA47</NID>
						<NAME>sceGe_driver_1A6BBA47</NAME>
					</FUNCTION>
					<FUNCTION>
						<NID>0x1DDA69CE</NID>
						<NAME>sceGe_driver_1DDA69CE</NAME>
					</FUNCTION>
					<FUNCTION>
						<NID>0x25D52F49</NID>
						<NAME>sceGe_driver_25D52F49</NAME>
					</FUNCTION>
					<FUNCTION>
						<NID>0x2BEAF4F0</NID>
						<NAME>sceGe_driver_2BEAF4F0</NAME>
					</FUNCTION>
					<FUNCTION>
						<NID>0x37EAFE13</NID>
						<NAME>sceGe_driver_37EAFE13</NAME>
					</FUNCTION>
					<FUNCTION>
						<NID>0x3B1AD135</NID>
						<NAME>sceGe_driver_3B1AD135</NAME>
					</FUNCTION>
					<FUNCTION>
						<NID>0x3B30A5CC</NID>
						<NAME>sceGe_driver_3B30A5CC</NAME>
					</FUNCTION>
					<FUNCTION>
						<NID>0x51C708EC</NID>
						<NAME>sceGe_driver_51C708EC</NAME>
					</FUNCTION>
					<FUNCTION>
						<NID>0x58624E06</NID>
						<NAME>sceGe_driver_58624E06</NAME>
					</FUNCTION>
					<FUNCTION>
						<NID>0x69C787E1</NID>
						<NAME>sceGe_driver_69C787E1</NAME>
					</FUNCTION>
					<FUNCTION>
						<NID>0x7E8DFAC9</NID>
						<NAME>sceGe_driver_7E8DFAC9</NAME>
					</FUNCTION>
					<FUNCTION>
						<NID>0x8299C54C</NID>
						<NAME>sceGe_driver_8299C54C</NAME>
					</FUNCTION>
					<FUNCTION>
						<NID>0x84DF53A6</NID>
						<NAME>sceGe_driver_84DF53A6</NAME>
					</FUNCTION>
					<FUNCTION>
						<NID>0x854B1235</NID>
						<NAME>sceGe_driver_854B1235</NAME>
					</FUNCTION>
					<FUNCTION>
						<NID>0x8EB2762D</NID>
						<NAME>sceGe_driver_8EB2762D</NAME>
					</FUNCTION>
					<FUNCTION>
						<NID>0x969516DE</NID>
						<NAME>sceGe_driver_969516DE</NAME>
					</FUNCTION>
					<FUNCTION>
						<NID>0x98FD5CA9</NID>
						<NAME>sceGe_driver_98FD5CA9</NAME>
					</FUNCTION>
					<FUNCTION>
						<NID>0xA402A161</NID>
						<NAME>sceGe_driver_A402A161</NAME>
					</FUNCTION>
					<FUNCTION>
						<NID>0xA7254F4F</NID>
						<NAME>sceGe_driver_A7254F4F</NAME>
					</FUNCTION>
					<FUNCTION>
						<NID>0xAE983AF9</NID>
						<NAME>sceGe_driver_AE983AF9</NAME>
					</FUNCTION>
					<FUNCTION>
						<NID>0xB5891BE0</NID>
						<NAME>sceGe_driver_B5891BE0</NAME>
					</FUNCTION>
					<FUNCTION>
						<NID>0xB6D2B704</NID>
						<NAME>sceGe_driver_B6D2B704</NAME>
					</FUNCTION>
					<FUNCTION>
						<NID>0xC080B8F4</NID>
						<NAME>sceGe_driver_C080B8F4</NAME>
					</FUNCTION>
					<FUNCTION>
						<NID>0xC545B81E</NID>
						<NAME>sceGe_driver_C545B81E</NAME>
					</FUNCTION>
					<FUNCTION>
						<NID>0xCDE4BE78</NID>
						<NAME>sceGe_driver_CDE4BE78</NAME>
					</FUNCTION>
					<FUNCTION>
						<NID>0xD2BF1F07</NID>
						<NAME>sceGe_driver_D2BF1F07</NAME>
					</FUNCTION>
					<FUNCTION>
						<NID>0xD7268C51</NID>
						<NAME>sceGe_driver_D7268C51</NAME>
					</FUNCTION>
					<FUNCTION>
						<NID>0xDC09D302</NID>
						<NAME>sceGe_driver_DC09D302</NAME>
					</FUNCTION>
					<FUNCTION>
						<NID>0xF5423CAA</NID>
						<NAME>sceGe_driver_F5423CAA</NAME>
					</FUNCTION>
					<FUNCTION>
						<NID>0xF5A03D9B</NID>
						<NAME>sceGe_driver_F5A03D9B</NAME>
					</FUNCTION>
					<FUNCTION>
						<NID>0xF99CE896</NID>
						<NAME>sceGe_driver_F99CE896</NAME>
					</FUNCTION>
				</FUNCTIONS>
			</LIBRARY>
			<LIBRARY>
				<NAME>sceGe_user</NAME>
				<FLAGS>0x40010011</FLAGS>
				<FUNCTIONS>
					<FUNCTION>
						<NID>0x03444EB4</NID>
						<NAME>sceGeListSync</NAME>
					</FUNCTION>
					<FUNCTION>
						<NID>0x05DB22CE</NID>
						<NAME>sceGeUnsetCallback</NAME>
					</FUNCTION>
					<FUNCTION>
						<NID>0x0BF608FB</NID>
						<NAME>sceGeRestoreContext</NAME>
					</FUNCTION>
					<FUNCTION>
						<NID>0x1C0D95A6</NID>
						<NAME>sceGeListEnQueueHead</NAME>
					</FUNCTION>
					<FUNCTION>
						<NID>0x1F6752AD</NID>
						<NAME>sceGeEdramGetSize</NAME>
					</FUNCTION>
					<FUNCTION>
						<NID>0x438A385A</NID>
						<NAME>sceGeSaveContext</NAME>
					</FUNCTION>
					<FUNCTION>
						<NID>0x4C06E472</NID>
						<NAME>sceGeContinue</NAME>
					</FUNCTION>
					<FUNCTION>
						<NID>0x57C8945B</NID>
						<NAME>sceGeGetMtx</NAME>
					</FUNCTION>
					<FUNCTION>
						<NID>0x5FB86AB0</NID>
						<NAME>sceGeListDeQueue</NAME>
					</FUNCTION>
					<FUNCTION>
						<NID>0xA4FC06A4</NID>
						<NAME>sceGeSetCallback</NAME>
					</FUNCTION>
					<FUNCTION>
						<NID>0xAB49E76A</NID>
						<NAME>sceGeListEnQueue</NAME>
					</FUNCTION>
					<FUNCTION>
						<NID>0xB287BD61</NID>
						<NAME>sceGeDrawSync</NAME>
					</FUNCTION>
					<FUNCTION>
						<NID>0xB448EC0D</NID>
						<NAME>sceGeBreak</NAME>
					</FUNCTION>
					<FUNCTION>
						<NID>0xB77905EA</NID>
						<NAME>sceGeEdramSetAddrTranslation</NAME>
					</FUNCTION>
					<FUNCTION>
						<NID>0xDC93CFEF</NID>
						<NAME>sceGeGetCmd</NAME>
					</FUNCTION>
					<FUNCTION>
						<NID>0xE0D68148</NID>
						<NAME>sceGeListUpdateStallAddr</NAME>
					</FUNCTION>
					<FUNCTION>
						<NID>0xE47E40E4</NID>
						<NAME>sceGeEdramGetAddr</NAME>
					</FUNCTION>
					<FUNCTION>
						<NID>0xE66CB92E</NID>
						<NAME>sceGeGetStack</NAME>
					</FUNCTION>
				</FUNCTIONS>
			</LIBRARY>
		</LIBRARIES>
		</PRXFILE>
	</PRXFILES>
</PSPLIBDOC>
