<?xml version="1.0" ?>
<?xml-stylesheet type="text/xsl" href="psplibdocdisplay.xsl" ?>
<PSPLIBDOC>
	<PRXFILES>
		<PRXFILE>
		<PRX>lepton_updateXXX.prx</PRX>
		<PRXNAME>SyncProgressBar</PRXNAME>
		<LIBRARIES>
			<LIBRARY>
				<NAME>sceLeptonUpdate</NAME>
				<FLAGS>0x40010011</FLAGS>
				<FUNCTIONS>
					<FUNCTION>
						<NID>0xE593B09C</NID>
						<NAME>sceLeptonUpdateInit</NAME>
					</FUNCTION>
					<FUNCTION>
						<NID>0xF30C2D7A</NID>
						<NAME>sceLeptonUpdateEnd</NAME>
					</FUNCTION>
					<FUNCTION>
						<NID>0x7E2759BB</NID>
						<NAME>sceLeptonUpdateGetVersion</NAME>
					</FUNCTION>
					<FUNCTION>
						<NID>0x006D3BF8</NID>
						<NAME>sceLeptonUpdateSetDebugCode</NAME>
					</FUNCTION>
					<FUNCTION>
						<NID>0x14847053</NID>
						<NAME>sceLeptonUpdateLeptonPowerOn</NAME>
					</FUNCTION>
					<FUNCTION>
						<NID>0x281E8901</NID>
						<NAME>sceLeptonUpdateLeptonPowerOff</NAME>
					</FUNCTION>
					<FUNCTION>
						<NID>0x6B81B9F7</NID>
						<NAME>sceLeptonUpdateReleaseUmdDetectHandler</NAME>
					</FUNCTION>
				</FUNCTIONS>
			</LIBRARY>
			<LIBRARY>
				<NAME>sceLeptonUpdate_driver</NAME>
				<FLAGS>0x00010011</FLAGS>
				<FUNCTIONS>
					<FUNCTION>
						<NID>0xE593B09C</NID>
						<NAME>sceLeptonUpdateInit</NAME>
					</FUNCTION>
					<FUNCTION>
						<NID>0xF30C2D7A</NID>
						<NAME>sceLeptonUpdateEnd</NAME>
					</FUNCTION>
					<FUNCTION>
						<NID>0x7E2759BB</NID>
						<NAME>sceLeptonUpdateGetVersion</NAME>
					</FUNCTION>
					<FUNCTION>
						<NID>0x006D3BF8</NID>
						<NAME>sceLeptonUpdateSetDebugCode</NAME>
					</FUNCTION>
					<FUNCTION>
						<NID>0x14847053</NID>
						<NAME>sceLeptonUpdateLeptonPowerOn</NAME>
					</FUNCTION>
					<FUNCTION>
						<NID>0x281E8901</NID>
						<NAME>sceLeptonUpdateLeptonPowerOff</NAME>
					</FUNCTION>
					<FUNCTION>
						<NID>0x6B81B9F7</NID>
						<NAME>sceLeptonUpdateReleaseUmdDetectHandler</NAME>
					</FUNCTION>
				</FUNCTIONS>
			</LIBRARY>
		</LIBRARIES>
		</PRXFILE>
	</PRXFILES>
</PSPLIBDOC>
