<?xml version="1.0" ?>
<?xml-stylesheet type="text/xsl" href="psplibdocdisplay.xsl" ?>
<PSPLIBDOC>
	<PRXFILES>
		<PRXFILE>
		<PRX>vsh/module/oneseg_core.prx</PRX>
		<PRXNAME>oneseg_core_module</PRXNAME>
		<LIBRARIES>
			<LIBRARY>
				<NAME>onesegSdk</NAME>
				<FLAGS>0x00090011</FLAGS>
				<FUNCTIONS>
					<FUNCTION>
						<NID>0x239EDAE8</NID>
						<NAME>onesegSdk_239EDAE8</NAME>
					</FUNCTION>
				</FUNCTIONS>
			</LIBRARY>
			<LIBRARY>
				<NAME>onesegSdkCore</NAME>
				<FLAGS>0x00090011</FLAGS>
				<FUNCTIONS>
					<FUNCTION>
						<NID>0x00565C73</NID>
						<NAME>onesegSdkCore_00565C73</NAME>
					</FUNCTION>
					<FUNCTION>
						<NID>0x014322DA</NID>
						<NAME>onesegSdkCore_014322DA</NAME>
					</FUNCTION>
					<FUNCTION>
						<NID>0x02A82327</NID>
						<NAME>onesegSdkCore_02A82327</NAME>
					</FUNCTION>
					<FUNCTION>
						<NID>0x07BAA6AB</NID>
						<NAME>onesegSdkCore_07BAA6AB</NAME>
					</FUNCTION>
					<FUNCTION>
						<NID>0x0F660BDE</NID>
						<NAME>onesegSdkCore_0F660BDE</NAME>
					</FUNCTION>
					<FUNCTION>
						<NID>0x0FA9E7D2</NID>
						<NAME>onesegSdkCore_0FA9E7D2</NAME>
					</FUNCTION>
					<FUNCTION>
						<NID>0x1786513F</NID>
						<NAME>onesegSdkCore_1786513F</NAME>
					</FUNCTION>
					<FUNCTION>
						<NID>0x18EC071A</NID>
						<NAME>onesegSdkCore_18EC071A</NAME>
					</FUNCTION>
					<FUNCTION>
						<NID>0x1ACB415D</NID>
						<NAME>onesegSdkCore_1ACB415D</NAME>
					</FUNCTION>
					<FUNCTION>
						<NID>0x1BFE7BBC</NID>
						<NAME>onesegSdkCore_1BFE7BBC</NAME>
					</FUNCTION>
					<FUNCTION>
						<NID>0x1D00AC99</NID>
						<NAME>onesegSdkCore_1D00AC99</NAME>
					</FUNCTION>
					<FUNCTION>
						<NID>0x1F8D6292</NID>
						<NAME>onesegSdkCore_1F8D6292</NAME>
					</FUNCTION>
					<FUNCTION>
						<NID>0x1FC4079F</NID>
						<NAME>onesegSdkCore_1FC4079F</NAME>
					</FUNCTION>
					<FUNCTION>
						<NID>0x22437F04</NID>
						<NAME>onesegSdkCore_22437F04</NAME>
					</FUNCTION>
					<FUNCTION>
						<NID>0x23294F50</NID>
						<NAME>onesegSdkCore_23294F50</NAME>
					</FUNCTION>
					<FUNCTION>
						<NID>0x246BFCD9</NID>
						<NAME>onesegSdkCore_246BFCD9</NAME>
					</FUNCTION>
					<FUNCTION>
						<NID>0x257DFA20</NID>
						<NAME>onesegSdkCore_257DFA20</NAME>
					</FUNCTION>
					<FUNCTION>
						<NID>0x25893CF1</NID>
						<NAME>onesegSdkCore_25893CF1</NAME>
					</FUNCTION>
					<FUNCTION>
						<NID>0x2797088E</NID>
						<NAME>onesegSdkCore_2797088E</NAME>
					</FUNCTION>
					<FUNCTION>
						<NID>0x297BCD6E</NID>
						<NAME>onesegSdkCore_297BCD6E</NAME>
					</FUNCTION>
					<FUNCTION>
						<NID>0x29814BCF</NID>
						<NAME>onesegSdkCore_29814BCF</NAME>
					</FUNCTION>
					<FUNCTION>
						<NID>0x29F65B66</NID>
						<NAME>onesegSdkCore_29F65B66</NAME>
					</FUNCTION>
					<FUNCTION>
						<NID>0x2B42DB44</NID>
						<NAME>onesegSdkCore_2B42DB44</NAME>
					</FUNCTION>
					<FUNCTION>
						<NID>0x2E32B2D9</NID>
						<NAME>onesegSdkCore_2E32B2D9</NAME>
					</FUNCTION>
					<FUNCTION>
						<NID>0x2E4F2374</NID>
						<NAME>onesegSdkCore_2E4F2374</NAME>
					</FUNCTION>
					<FUNCTION>
						<NID>0x38F624CA</NID>
						<NAME>onesegSdkCore_38F624CA</NAME>
					</FUNCTION>
					<FUNCTION>
						<NID>0x3B9B8073</NID>
						<NAME>onesegSdkCore_3B9B8073</NAME>
					</FUNCTION>
					<FUNCTION>
						<NID>0x3BD4CA31</NID>
						<NAME>onesegSdkCore_3BD4CA31</NAME>
					</FUNCTION>
					<FUNCTION>
						<NID>0x3ECA9AC8</NID>
						<NAME>onesegSdkCore_3ECA9AC8</NAME>
					</FUNCTION>
					<FUNCTION>
						<NID>0x46053998</NID>
						<NAME>onesegSdkCore_46053998</NAME>
					</FUNCTION>
					<FUNCTION>
						<NID>0x574957C0</NID>
						<NAME>onesegSdkCore_574957C0</NAME>
					</FUNCTION>
					<FUNCTION>
						<NID>0x5B5BCA2A</NID>
						<NAME>onesegSdkCore_5B5BCA2A</NAME>
					</FUNCTION>
					<FUNCTION>
						<NID>0x5EB7A8F8</NID>
						<NAME>onesegSdkCore_5EB7A8F8</NAME>
					</FUNCTION>
					<FUNCTION>
						<NID>0x66CDA537</NID>
						<NAME>onesegSdkCore_66CDA537</NAME>
					</FUNCTION>
					<FUNCTION>
						<NID>0x6C5443C6</NID>
						<NAME>onesegSdkCore_6C5443C6</NAME>
					</FUNCTION>
					<FUNCTION>
						<NID>0x6D929303</NID>
						<NAME>onesegSdkCore_6D929303</NAME>
					</FUNCTION>
					<FUNCTION>
						<NID>0x6EC9C1F9</NID>
						<NAME>onesegSdkCore_6EC9C1F9</NAME>
					</FUNCTION>
					<FUNCTION>
						<NID>0x735BE2A2</NID>
						<NAME>onesegSdkCore_735BE2A2</NAME>
					</FUNCTION>
					<FUNCTION>
						<NID>0x78110A7F</NID>
						<NAME>onesegSdkCore_78110A7F</NAME>
					</FUNCTION>
					<FUNCTION>
						<NID>0x838A1E79</NID>
						<NAME>onesegSdkCore_838A1E79</NAME>
					</FUNCTION>
					<FUNCTION>
						<NID>0x859214D8</NID>
						<NAME>onesegSdkCore_859214D8</NAME>
					</FUNCTION>
					<FUNCTION>
						<NID>0x877CB4F9</NID>
						<NAME>onesegSdkCore_877CB4F9</NAME>
					</FUNCTION>
					<FUNCTION>
						<NID>0x878B398A</NID>
						<NAME>onesegSdkCore_878B398A</NAME>
					</FUNCTION>
					<FUNCTION>
						<NID>0x95289BED</NID>
						<NAME>onesegSdkCore_95289BED</NAME>
					</FUNCTION>
					<FUNCTION>
						<NID>0x95B01BBE</NID>
						<NAME>onesegSdkCore_95B01BBE</NAME>
					</FUNCTION>
					<FUNCTION>
						<NID>0x97071846</NID>
						<NAME>onesegSdkCore_97071846</NAME>
					</FUNCTION>
					<FUNCTION>
						<NID>0x9AE42F8C</NID>
						<NAME>onesegSdkCore_9AE42F8C</NAME>
					</FUNCTION>
					<FUNCTION>
						<NID>0x9B6D848C</NID>
						<NAME>onesegSdkCore_9B6D848C</NAME>
					</FUNCTION>
					<FUNCTION>
						<NID>0x9D072C28</NID>
						<NAME>onesegSdkCore_9D072C28</NAME>
					</FUNCTION>
					<FUNCTION>
						<NID>0x9DFB2C64</NID>
						<NAME>onesegSdkCore_9DFB2C64</NAME>
					</FUNCTION>
					<FUNCTION>
						<NID>0xA50A47BF</NID>
						<NAME>onesegSdkCore_A50A47BF</NAME>
					</FUNCTION>
					<FUNCTION>
						<NID>0xA66140B4</NID>
						<NAME>onesegSdkCore_A66140B4</NAME>
					</FUNCTION>
					<FUNCTION>
						<NID>0xA67DA839</NID>
						<NAME>onesegSdkCore_A67DA839</NAME>
					</FUNCTION>
					<FUNCTION>
						<NID>0xA91C2037</NID>
						<NAME>onesegSdkCore_A91C2037</NAME>
					</FUNCTION>
					<FUNCTION>
						<NID>0xAAD37865</NID>
						<NAME>onesegSdkCore_AAD37865</NAME>
					</FUNCTION>
					<FUNCTION>
						<NID>0xADCCA76D</NID>
						<NAME>onesegSdkCore_ADCCA76D</NAME>
					</FUNCTION>
					<FUNCTION>
						<NID>0xAF61DCF4</NID>
						<NAME>onesegSdkCore_AF61DCF4</NAME>
					</FUNCTION>
					<FUNCTION>
						<NID>0xB0940C84</NID>
						<NAME>onesegSdkCore_B0940C84</NAME>
					</FUNCTION>
					<FUNCTION>
						<NID>0xB554C052</NID>
						<NAME>onesegSdkCore_B554C052</NAME>
					</FUNCTION>
					<FUNCTION>
						<NID>0xB5554872</NID>
						<NAME>onesegSdkCore_B5554872</NAME>
					</FUNCTION>
					<FUNCTION>
						<NID>0xB713B786</NID>
						<NAME>onesegSdkCore_B713B786</NAME>
					</FUNCTION>
					<FUNCTION>
						<NID>0xB94420F9</NID>
						<NAME>onesegSdkCore_B94420F9</NAME>
					</FUNCTION>
					<FUNCTION>
						<NID>0xC13FF004</NID>
						<NAME>onesegSdkCore_C13FF004</NAME>
					</FUNCTION>
					<FUNCTION>
						<NID>0xC56F59B8</NID>
						<NAME>onesegSdkCore_C56F59B8</NAME>
					</FUNCTION>
					<FUNCTION>
						<NID>0xC65BBBDC</NID>
						<NAME>onesegSdkCore_C65BBBDC</NAME>
					</FUNCTION>
					<FUNCTION>
						<NID>0xC65BF203</NID>
						<NAME>onesegSdkCore_C65BF203</NAME>
					</FUNCTION>
					<FUNCTION>
						<NID>0xC68F14A9</NID>
						<NAME>onesegSdkCore_C68F14A9</NAME>
					</FUNCTION>
					<FUNCTION>
						<NID>0xC7E3CDBB</NID>
						<NAME>onesegSdkCore_C7E3CDBB</NAME>
					</FUNCTION>
					<FUNCTION>
						<NID>0xC9C42CA8</NID>
						<NAME>onesegSdkCore_C9C42CA8</NAME>
					</FUNCTION>
					<FUNCTION>
						<NID>0xD5EFD0FA</NID>
						<NAME>onesegSdkCore_D5EFD0FA</NAME>
					</FUNCTION>
					<FUNCTION>
						<NID>0xDCA74DCF</NID>
						<NAME>onesegSdkCore_DCA74DCF</NAME>
					</FUNCTION>
					<FUNCTION>
						<NID>0xDD581FB8</NID>
						<NAME>onesegSdkCore_DD581FB8</NAME>
					</FUNCTION>
					<FUNCTION>
						<NID>0xDE141C98</NID>
						<NAME>onesegSdkCore_DE141C98</NAME>
					</FUNCTION>
					<FUNCTION>
						<NID>0xDE47A295</NID>
						<NAME>onesegSdkCore_DE47A295</NAME>
					</FUNCTION>
					<FUNCTION>
						<NID>0xDE90FBCF</NID>
						<NAME>onesegSdkCore_DE90FBCF</NAME>
					</FUNCTION>
					<FUNCTION>
						<NID>0xE407F54E</NID>
						<NAME>onesegSdkCore_E407F54E</NAME>
					</FUNCTION>
					<FUNCTION>
						<NID>0xE52C2A09</NID>
						<NAME>onesegSdkCore_E52C2A09</NAME>
					</FUNCTION>
					<FUNCTION>
						<NID>0xEC35AE0E</NID>
						<NAME>onesegSdkCore_EC35AE0E</NAME>
					</FUNCTION>
					<FUNCTION>
						<NID>0xED582126</NID>
						<NAME>onesegSdkCore_ED582126</NAME>
					</FUNCTION>
					<FUNCTION>
						<NID>0xEE0853A1</NID>
						<NAME>onesegSdkCore_EE0853A1</NAME>
					</FUNCTION>
					<FUNCTION>
						<NID>0xF56826F7</NID>
						<NAME>onesegSdkCore_F56826F7</NAME>
					</FUNCTION>
					<FUNCTION>
						<NID>0xF942A64D</NID>
						<NAME>onesegSdkCore_F942A64D</NAME>
					</FUNCTION>
					<FUNCTION>
						<NID>0xFC227770</NID>
						<NAME>onesegSdkCore_FC227770</NAME>
					</FUNCTION>
					<FUNCTION>
						<NID>0xFE99CE67</NID>
						<NAME>onesegSdkCore_FE99CE67</NAME>
					</FUNCTION>
					<FUNCTION>
						<NID>0xFF8CE0AF</NID>
						<NAME>onesegSdkCore_FF8CE0AF</NAME>
					</FUNCTION>
				</FUNCTIONS>
				<VARIABLES>
					<VARIABLE>
						<NID>0x5B6D3CC5</NID>
						<NAME>onesegSdkCore_5B6D3CC5</NAME>
					</VARIABLE>
					<VARIABLE>
						<NID>0xC3F94087</NID>
						<NAME>onesegSdkCore_C3F94087</NAME>
					</VARIABLE>
				</VARIABLES>
			</LIBRARY>
			<LIBRARY>
				<NAME>onesegHalToolbox</NAME>
				<FLAGS>0x00090011</FLAGS>
				<FUNCTIONS>
					<FUNCTION>
						<NID>0x21E5600F</NID>
						<NAME>onesegHalToolbox_21E5600F</NAME>
					</FUNCTION>
					<FUNCTION>
						<NID>0x35CAA030</NID>
						<NAME>onesegHalToolbox_35CAA030</NAME>
					</FUNCTION>
					<FUNCTION>
						<NID>0x36A48AF0</NID>
						<NAME>onesegHalToolbox_36A48AF0</NAME>
					</FUNCTION>
					<FUNCTION>
						<NID>0x38BF2A89</NID>
						<NAME>onesegHalToolbox_38BF2A89</NAME>
					</FUNCTION>
					<FUNCTION>
						<NID>0x3FCF5660</NID>
						<NAME>onesegHalToolbox_3FCF5660</NAME>
					</FUNCTION>
					<FUNCTION>
						<NID>0x53B2ECDD</NID>
						<NAME>onesegHalToolbox_53B2ECDD</NAME>
					</FUNCTION>
					<FUNCTION>
						<NID>0x5D026D4E</NID>
						<NAME>onesegHalToolbox_5D026D4E</NAME>
					</FUNCTION>
					<FUNCTION>
						<NID>0x7A7C971B</NID>
						<NAME>onesegHalToolbox_7A7C971B</NAME>
					</FUNCTION>
					<FUNCTION>
						<NID>0x896D6109</NID>
						<NAME>onesegHalToolbox_896D6109</NAME>
					</FUNCTION>
					<FUNCTION>
						<NID>0x8C50868C</NID>
						<NAME>onesegHalToolbox_8C50868C</NAME>
					</FUNCTION>
					<FUNCTION>
						<NID>0x92CE3260</NID>
						<NAME>onesegHalToolbox_92CE3260</NAME>
					</FUNCTION>
					<FUNCTION>
						<NID>0x996928FF</NID>
						<NAME>onesegHalToolbox_996928FF</NAME>
					</FUNCTION>
					<FUNCTION>
						<NID>0xA5B6534C</NID>
						<NAME>onesegHalToolbox_A5B6534C</NAME>
					</FUNCTION>
					<FUNCTION>
						<NID>0xB503443B</NID>
						<NAME>onesegHalToolbox_B503443B</NAME>
					</FUNCTION>
					<FUNCTION>
						<NID>0xC17258E3</NID>
						<NAME>onesegHalToolbox_C17258E3</NAME>
					</FUNCTION>
					<FUNCTION>
						<NID>0xEAA7BE5A</NID>
						<NAME>onesegHalToolbox_EAA7BE5A</NAME>
					</FUNCTION>
					<FUNCTION>
						<NID>0xFAD1DB25</NID>
						<NAME>onesegHalToolbox_FAD1DB25</NAME>
					</FUNCTION>
				</FUNCTIONS>
			</LIBRARY>
			<LIBRARY>
				<NAME>onesegSal</NAME>
				<FLAGS>0x00090011</FLAGS>
				<FUNCTIONS>
					<FUNCTION>
						<NID>0x00850EAA</NID>
						<NAME>onesegSal_00850EAA</NAME>
					</FUNCTION>
					<FUNCTION>
						<NID>0x020B3CC6</NID>
						<NAME>onesegSal_020B3CC6</NAME>
					</FUNCTION>
					<FUNCTION>
						<NID>0x0886DCE2</NID>
						<NAME>onesegSal_0886DCE2</NAME>
					</FUNCTION>
					<FUNCTION>
						<NID>0x099DBC39</NID>
						<NAME>onesegSal_099DBC39</NAME>
					</FUNCTION>
					<FUNCTION>
						<NID>0x0F83A1AA</NID>
						<NAME>onesegSal_0F83A1AA</NAME>
					</FUNCTION>
					<FUNCTION>
						<NID>0x12F99955</NID>
						<NAME>onesegSal_12F99955</NAME>
					</FUNCTION>
					<FUNCTION>
						<NID>0x1EFAB50D</NID>
						<NAME>onesegSal_1EFAB50D</NAME>
					</FUNCTION>
					<FUNCTION>
						<NID>0x265926E7</NID>
						<NAME>onesegSal_265926E7</NAME>
					</FUNCTION>
					<FUNCTION>
						<NID>0x2D9F26C3</NID>
						<NAME>onesegSal_2D9F26C3</NAME>
					</FUNCTION>
					<FUNCTION>
						<NID>0x363E72DD</NID>
						<NAME>onesegSal_363E72DD</NAME>
					</FUNCTION>
					<FUNCTION>
						<NID>0x39AF4F3B</NID>
						<NAME>onesegSal_39AF4F3B</NAME>
					</FUNCTION>
					<FUNCTION>
						<NID>0x3B70E875</NID>
						<NAME>onesegSal_3B70E875</NAME>
					</FUNCTION>
					<FUNCTION>
						<NID>0x3F2ADE66</NID>
						<NAME>onesegSal_3F2ADE66</NAME>
					</FUNCTION>
					<FUNCTION>
						<NID>0x433AC527</NID>
						<NAME>onesegSal_433AC527</NAME>
					</FUNCTION>
					<FUNCTION>
						<NID>0x456203B0</NID>
						<NAME>onesegSal_456203B0</NAME>
					</FUNCTION>
					<FUNCTION>
						<NID>0x4F5AD890</NID>
						<NAME>onesegSal_4F5AD890</NAME>
					</FUNCTION>
					<FUNCTION>
						<NID>0x533835A6</NID>
						<NAME>onesegSal_533835A6</NAME>
					</FUNCTION>
					<FUNCTION>
						<NID>0x5FC83C98</NID>
						<NAME>onesegSal_5FC83C98</NAME>
					</FUNCTION>
					<FUNCTION>
						<NID>0x6086187E</NID>
						<NAME>onesegSal_6086187E</NAME>
					</FUNCTION>
					<FUNCTION>
						<NID>0x653384D2</NID>
						<NAME>onesegSal_653384D2</NAME>
					</FUNCTION>
					<FUNCTION>
						<NID>0x6763AD27</NID>
						<NAME>onesegSal_6763AD27</NAME>
					</FUNCTION>
					<FUNCTION>
						<NID>0x69D4A9F4</NID>
						<NAME>onesegSal_69D4A9F4</NAME>
					</FUNCTION>
					<FUNCTION>
						<NID>0x6DEC6268</NID>
						<NAME>onesegSal_6DEC6268</NAME>
					</FUNCTION>
					<FUNCTION>
						<NID>0x71AED199</NID>
						<NAME>onesegSal_71AED199</NAME>
					</FUNCTION>
					<FUNCTION>
						<NID>0x71C6AB48</NID>
						<NAME>onesegSal_71C6AB48</NAME>
					</FUNCTION>
					<FUNCTION>
						<NID>0x74AF7C06</NID>
						<NAME>onesegSal_74AF7C06</NAME>
					</FUNCTION>
					<FUNCTION>
						<NID>0x78B02C08</NID>
						<NAME>onesegSal_78B02C08</NAME>
					</FUNCTION>
					<FUNCTION>
						<NID>0x8A14C632</NID>
						<NAME>onesegSal_8A14C632</NAME>
					</FUNCTION>
					<FUNCTION>
						<NID>0x8B2F9A5B</NID>
						<NAME>onesegSal_8B2F9A5B</NAME>
					</FUNCTION>
					<FUNCTION>
						<NID>0x8FE81670</NID>
						<NAME>onesegSal_8FE81670</NAME>
					</FUNCTION>
					<FUNCTION>
						<NID>0x950E5178</NID>
						<NAME>onesegSal_950E5178</NAME>
					</FUNCTION>
					<FUNCTION>
						<NID>0x9CBB0F5D</NID>
						<NAME>onesegSal_9CBB0F5D</NAME>
					</FUNCTION>
					<FUNCTION>
						<NID>0xA74C56C6</NID>
						<NAME>onesegSal_A74C56C6</NAME>
					</FUNCTION>
					<FUNCTION>
						<NID>0xAA6EEB53</NID>
						<NAME>onesegSal_AA6EEB53</NAME>
					</FUNCTION>
					<FUNCTION>
						<NID>0xAE582306</NID>
						<NAME>onesegSal_AE582306</NAME>
					</FUNCTION>
					<FUNCTION>
						<NID>0xB46CEECD</NID>
						<NAME>onesegSal_B46CEECD</NAME>
					</FUNCTION>
					<FUNCTION>
						<NID>0xBABF0A73</NID>
						<NAME>onesegSal_BABF0A73</NAME>
					</FUNCTION>
					<FUNCTION>
						<NID>0xBF12FF51</NID>
						<NAME>onesegSal_BF12FF51</NAME>
					</FUNCTION>
					<FUNCTION>
						<NID>0xDB69838E</NID>
						<NAME>onesegSal_DB69838E</NAME>
					</FUNCTION>
					<FUNCTION>
						<NID>0xE37427BE</NID>
						<NAME>onesegSal_E37427BE</NAME>
					</FUNCTION>
					<FUNCTION>
						<NID>0xE549E5A9</NID>
						<NAME>onesegSal_E549E5A9</NAME>
					</FUNCTION>
					<FUNCTION>
						<NID>0xE64CF915</NID>
						<NAME>onesegSal_E64CF915</NAME>
					</FUNCTION>
					<FUNCTION>
						<NID>0xF2DADC23</NID>
						<NAME>onesegSal_F2DADC23</NAME>
					</FUNCTION>
					<FUNCTION>
						<NID>0xFB5FE576</NID>
						<NAME>onesegSal_FB5FE576</NAME>
					</FUNCTION>
					<FUNCTION>
						<NID>0xFDC7AC2A</NID>
						<NAME>onesegSal_FDC7AC2A</NAME>
					</FUNCTION>
				</FUNCTIONS>
			</LIBRARY>
			<LIBRARY>
				<NAME>sceNetApctl</NAME>
				<FLAGS>0x00090011</FLAGS>
				<FUNCTIONS>
					<FUNCTION>
						<NID>0x5963991B</NID>
						<NAME>sceNetApctlDelHandler</NAME>
					</FUNCTION>
					<FUNCTION>
						<NID>0x8ABADD51</NID>
						<NAME>sceNetApctlAddHandler</NAME>
					</FUNCTION>
				</FUNCTIONS>
			</LIBRARY>
			<LIBRARY>
				<NAME>sceHttp</NAME>
				<FLAGS>0x00090011</FLAGS>
				<FUNCTIONS>
					<FUNCTION>
						<NID>0x0282A3BD</NID>
						<NAME>sceHttpGetContentLength</NAME>
					</FUNCTION>
					<FUNCTION>
						<NID>0x0B12ABFB</NID>
						<NAME>sceHttpDisableCookie</NAME>
					</FUNCTION>
					<FUNCTION>
						<NID>0x2255551E</NID>
						<NAME>sceHttpGetNetworkPspError</NAME>
					</FUNCTION>
					<FUNCTION>
						<NID>0x3EABA285</NID>
						<NAME>sceHttpAddExtraHeader</NAME>
					</FUNCTION>
					<FUNCTION>
						<NID>0x4CC7D78F</NID>
						<NAME>sceHttpGetStatusCode</NAME>
					</FUNCTION>
					<FUNCTION>
						<NID>0x5152773B</NID>
						<NAME>sceHttpDeleteConnection</NAME>
					</FUNCTION>
					<FUNCTION>
						<NID>0x59E6D16F</NID>
						<NAME>sceHttpEnableCache</NAME>
					</FUNCTION>
					<FUNCTION>
						<NID>0x9B1F1F36</NID>
						<NAME>sceHttpCreateTemplate</NAME>
					</FUNCTION>
					<FUNCTION>
						<NID>0xA4496DE5</NID>
						<NAME>sceHttpSetRedirectCallback</NAME>
					</FUNCTION>
					<FUNCTION>
						<NID>0xA5512E01</NID>
						<NAME>sceHttpDeleteRequest</NAME>
					</FUNCTION>
					<FUNCTION>
						<NID>0xAE948FEE</NID>
						<NAME>sceHttpDisableAuth</NAME>
					</FUNCTION>
					<FUNCTION>
						<NID>0xB509B09E</NID>
						<NAME>sceHttpCreateRequestWithURL</NAME>
					</FUNCTION>
					<FUNCTION>
						<NID>0xBB70706F</NID>
						<NAME>sceHttpSendRequest</NAME>
					</FUNCTION>
					<FUNCTION>
						<NID>0xC10B6BD9</NID>
						<NAME>sceHttpAbortRequest</NAME>
					</FUNCTION>
					<FUNCTION>
						<NID>0xCDF8ECB9</NID>
						<NAME>sceHttpCreateConnectionWithURL</NAME>
					</FUNCTION>
					<FUNCTION>
						<NID>0xDB266CCF</NID>
						<NAME>sceHttpGetAllHeader</NAME>
					</FUNCTION>
					<FUNCTION>
						<NID>0xEDEEB999</NID>
						<NAME>sceHttpReadData</NAME>
					</FUNCTION>
					<FUNCTION>
						<NID>0xFCF8C055</NID>
						<NAME>sceHttpDeleteTemplate</NAME>
					</FUNCTION>
				</FUNCTIONS>
			</LIBRARY>
			<LIBRARY>
				<NAME>sceWlanDrv</NAME>
				<FLAGS>0x40010011</FLAGS>
				<FUNCTIONS>
					<FUNCTION>
						<NID>0xD7763699</NID>
						<NAME>sceWlanGetSwitchState</NAME>
					</FUNCTION>
				</FUNCTIONS>
			</LIBRARY>
			<LIBRARY>
				<NAME>sceVaudio</NAME>
				<FLAGS>0x40010011</FLAGS>
				<FUNCTIONS>
					<FUNCTION>
						<NID>0x03B6807D</NID>
						<NAME>sceVaudioChReserve</NAME>
					</FUNCTION>
					<FUNCTION>
						<NID>0x67585DFD</NID>
						<NAME>sceVaudioChRelease</NAME>
					</FUNCTION>
					<FUNCTION>
						<NID>0x8986295E</NID>
						<NAME>sceVaudioOutputBlocking</NAME>
					</FUNCTION>
				</FUNCTIONS>
			</LIBRARY>
			<LIBRARY>
				<NAME>sceMpegbase</NAME>
				<FLAGS>0x40010011</FLAGS>
				<FUNCTIONS>
					<FUNCTION>
						<NID>0x7AC0321A</NID>
						<NAME>sceMpegBaseYCrCbCopy</NAME>
					</FUNCTION>
					<FUNCTION>
						<NID>0x91929A21</NID>
						<NAME>sceMpegBaseCscAvc</NAME>
					</FUNCTION>
					<FUNCTION>
						<NID>0xAC9E717E</NID>
						<NAME>sceMpegbase_AC9E717E</NAME>
					</FUNCTION>
				</FUNCTIONS>
			</LIBRARY>
			<LIBRARY>
				<NAME>sceMpeg</NAME>
				<FLAGS>0x00090011</FLAGS>
				<FUNCTIONS>
					<FUNCTION>
						<NID>0x0E3C2E9D</NID>
						<NAME>sceMpegAvcDecode</NAME>
					</FUNCTION>
					<FUNCTION>
						<NID>0x11F95CF1</NID>
						<NAME>sceMpegGetAvcNalAu</NAME>
					</FUNCTION>
					<FUNCTION>
						<NID>0x167AFD9E</NID>
						<NAME>sceMpegInitAu</NAME>
					</FUNCTION>
					<FUNCTION>
						<NID>0x606A4649</NID>
						<NAME>sceMpegDelete</NAME>
					</FUNCTION>
					<FUNCTION>
						<NID>0x6F314410</NID>
						<NAME>sceMpegAvcDecodeGetDecodeSEI</NAME>
					</FUNCTION>
					<FUNCTION>
						<NID>0x740FCCD1</NID>
						<NAME>sceMpegAvcDecodeStop</NAME>
					</FUNCTION>
					<FUNCTION>
						<NID>0x921FCCCF</NID>
						<NAME>sceMpegGetAvcEsAu</NAME>
					</FUNCTION>
					<FUNCTION>
						<NID>0xAB0E9556</NID>
						<NAME>sceMpeg_AB0E9556</NAME>
					</FUNCTION>
					<FUNCTION>
						<NID>0xC132E22F</NID>
						<NAME>sceMpegQueryMemSize</NAME>
					</FUNCTION>
					<FUNCTION>
						<NID>0xCF3547A2</NID>
						<NAME>sceMpegAvcDecodeDetail2</NAME>
					</FUNCTION>
					<FUNCTION>
						<NID>0xD8C5F121</NID>
						<NAME>sceMpegCreate</NAME>
					</FUNCTION>
				</FUNCTIONS>
			</LIBRARY>
			<LIBRARY>
				<NAME>sceAudiocodec</NAME>
				<FLAGS>0x40010011</FLAGS>
				<FUNCTIONS>
					<FUNCTION>
						<NID>0x59176A0F</NID>
						<NAME>sceAudiocodec_59176A0F</NAME>
					</FUNCTION>
					<FUNCTION>
						<NID>0x5B37EB1D</NID>
						<NAME>sceAudiocodecInit</NAME>
					</FUNCTION>
					<FUNCTION>
						<NID>0x70A703F8</NID>
						<NAME>sceAudiocodecDecode</NAME>
					</FUNCTION>
					<FUNCTION>
						<NID>0x9D3F790C</NID>
						<NAME>sceAudiocodeCheckNeedMem</NAME>
					</FUNCTION>
				</FUNCTIONS>
			</LIBRARY>
			<LIBRARY>
				<NAME>sceVshCommonUtil</NAME>
				<FLAGS>0x00010011</FLAGS>
				<FUNCTIONS>
					<FUNCTION>
						<NID>0x6D1BB739</NID>
						<NAME>sceVshCommonUtil_6D1BB739</NAME>
					</FUNCTION>
					<FUNCTION>
						<NID>0x83D156EF</NID>
						<NAME>sceVshCommonUtil_83D156EF</NAME>
					</FUNCTION>
					<FUNCTION>
						<NID>0x895AC0A2</NID>
						<NAME>sceVshCommonUtil_895AC0A2</NAME>
					</FUNCTION>
				</FUNCTIONS>
			</LIBRARY>
			<LIBRARY>
				<NAME>vsh</NAME>
				<FLAGS>0x00010011</FLAGS>
				<FUNCTIONS>
					<FUNCTION>
						<NID>0xF7350D2E</NID>
						<NAME>vsh_F7350D2E</NAME>
					</FUNCTION>
				</FUNCTIONS>
			</LIBRARY>
			<LIBRARY>
				<NAME>sceChnnlsv</NAME>
				<FLAGS>0x40010011</FLAGS>
				<FUNCTIONS>
					<FUNCTION>
						<NID>0x21BE78B4</NID>
						<NAME>sceChnnlsv_21BE78B4</NAME>
					</FUNCTION>
					<FUNCTION>
						<NID>0x850A7FA1</NID>
						<NAME>sceSdSetMember</NAME>
					</FUNCTION>
					<FUNCTION>
						<NID>0xABFDFC8B</NID>
						<NAME>sceSdCreateList</NAME>
					</FUNCTION>
					<FUNCTION>
						<NID>0xC4C494F8</NID>
						<NAME>sceSdGetLastIndex</NAME>
					</FUNCTION>
					<FUNCTION>
						<NID>0xE7833020</NID>
						<NAME>sceSdSetIndex</NAME>
					</FUNCTION>
					<FUNCTION>
						<NID>0xF21A1FCA</NID>
						<NAME>sceSdRemoveValue</NAME>
					</FUNCTION>
				</FUNCTIONS>
			</LIBRARY>
			<LIBRARY>
				<NAME>scePaf</NAME>
				<FLAGS>0x00010011</FLAGS>
				<FUNCTIONS>
					<FUNCTION>
						<NID>0x066E04FB</NID>
						<NAME>scePaf_066E04FB</NAME>
					</FUNCTION>
					<FUNCTION>
						<NID>0x1F5CABC0</NID>
						<NAME>scePaf_1F5CABC0</NAME>
					</FUNCTION>
					<FUNCTION>
						<NID>0x363D5877</NID>
						<NAME>scePaf_363D5877</NAME>
					</FUNCTION>
					<FUNCTION>
						<NID>0x36878B57</NID>
						<NAME>scePaf_36878B57</NAME>
					</FUNCTION>
					<FUNCTION>
						<NID>0x4131266B</NID>
						<NAME>scePaf_4131266B</NAME>
					</FUNCTION>
					<FUNCTION>
						<NID>0x4B17254D</NID>
						<NAME>scePaf_4B17254D</NAME>
					</FUNCTION>
					<FUNCTION>
						<NID>0x5C5B1B71</NID>
						<NAME>scePaf_5C5B1B71</NAME>
					</FUNCTION>
					<FUNCTION>
						<NID>0x658743BB</NID>
						<NAME>scePaf_658743BB</NAME>
					</FUNCTION>
					<FUNCTION>
						<NID>0x6F7856C4</NID>
						<NAME>scePaf_6F7856C4</NAME>
					</FUNCTION>
					<FUNCTION>
						<NID>0x8B1B76E1</NID>
						<NAME>scePaf_8B1B76E1</NAME>
					</FUNCTION>
					<FUNCTION>
						<NID>0x8E92F2FA</NID>
						<NAME>scePaf_8E92F2FA</NAME>
					</FUNCTION>
					<FUNCTION>
						<NID>0x916D3160</NID>
						<NAME>scePaf_916D3160</NAME>
					</FUNCTION>
					<FUNCTION>
						<NID>0x9375C183</NID>
						<NAME>scePaf_9375C183</NAME>
					</FUNCTION>
					<FUNCTION>
						<NID>0x98B0B575</NID>
						<NAME>scePaf_98B0B575</NAME>
					</FUNCTION>
					<FUNCTION>
						<NID>0xA329E340</NID>
						<NAME>scePaf_A329E340</NAME>
					</FUNCTION>
					<FUNCTION>
						<NID>0xB87310F2</NID>
						<NAME>scePaf_B87310F2</NAME>
					</FUNCTION>
					<FUNCTION>
						<NID>0xC1001284</NID>
						<NAME>scePaf_C1001284</NAME>
					</FUNCTION>
					<FUNCTION>
						<NID>0xC2369BD5</NID>
						<NAME>scePaf_C2369BD5</NAME>
					</FUNCTION>
					<FUNCTION>
						<NID>0xC3A28E77</NID>
						<NAME>scePaf_C3A28E77</NAME>
					</FUNCTION>
					<FUNCTION>
						<NID>0xE2579220</NID>
						<NAME>scePaf_E2579220</NAME>
					</FUNCTION>
					<FUNCTION>
						<NID>0xF9C60CF3</NID>
						<NAME>scePaf_F9C60CF3</NAME>
					</FUNCTION>
					<FUNCTION>
						<NID>0xFE9E046F</NID>
						<NAME>scePaf_FE9E046F</NAME>
					</FUNCTION>
				</FUNCTIONS>
				<VARIABLES>
					<VARIABLE>
						<NID>0x55720620</NID>
						<NAME>scePaf_55720620</NAME>
					</VARIABLE>
				</VARIABLES>
			</LIBRARY>
			<LIBRARY>
				<NAME>sceDisplay</NAME>
				<FLAGS>0x40010011</FLAGS>
				<FUNCTIONS>
					<FUNCTION>
						<NID>0x984C27E7</NID>
						<NAME>sceDisplayWaitVblankStart</NAME>
					</FUNCTION>
					<FUNCTION>
						<NID>0x9C6EAAD7</NID>
						<NAME>sceDisplayGetVcount</NAME>
					</FUNCTION>
				</FUNCTIONS>
			</LIBRARY>
			<LIBRARY>
				<NAME>IoFileMgrForUser</NAME>
				<FLAGS>0x40010011</FLAGS>
				<FUNCTIONS>
					<FUNCTION>
						<NID>0x42EC03AC</NID>
						<NAME>sceIoWrite</NAME>
					</FUNCTION>
					<FUNCTION>
						<NID>0x54F5FB11</NID>
						<NAME>sceIoDevctl</NAME>
					</FUNCTION>
					<FUNCTION>
						<NID>0x6A638D83</NID>
						<NAME>sceIoRead</NAME>
					</FUNCTION>
					<FUNCTION>
						<NID>0x779103A0</NID>
						<NAME>sceIoRename</NAME>
					</FUNCTION>
					<FUNCTION>
						<NID>0x810C4BC3</NID>
						<NAME>sceIoClose</NAME>
					</FUNCTION>
					<FUNCTION>
						<NID>0x06A70004</NID>
						<NAME>sceIoMkdir</NAME>
					</FUNCTION>
					<FUNCTION>
						<NID>0xAB96437F</NID>
						<NAME>sceIoSync</NAME>
					</FUNCTION>
					<FUNCTION>
						<NID>0xACE946E8</NID>
						<NAME>sceIoGetstat</NAME>
					</FUNCTION>
					<FUNCTION>
						<NID>0xB29DDF9C</NID>
						<NAME>sceIoDopen</NAME>
					</FUNCTION>
					<FUNCTION>
						<NID>0xE3EB004C</NID>
						<NAME>sceIoDread</NAME>
					</FUNCTION>
					<FUNCTION>
						<NID>0xEB092469</NID>
						<NAME>sceIoDclose</NAME>
					</FUNCTION>
					<FUNCTION>
						<NID>0xF27A9C51</NID>
						<NAME>sceIoRemove</NAME>
					</FUNCTION>
					<FUNCTION>
						<NID>0x109F50BC</NID>
						<NAME>sceIoOpen</NAME>
					</FUNCTION>
					<FUNCTION>
						<NID>0x27EB27B8</NID>
						<NAME>sceIoLseek</NAME>
					</FUNCTION>
				</FUNCTIONS>
			</LIBRARY>
			<LIBRARY>
				<NAME>Kernel_Library</NAME>
				<FLAGS>0x00010011</FLAGS>
				<FUNCTIONS>
					<FUNCTION>
						<NID>0x092968F4</NID>
						<NAME>sceKernelCpuSuspendIntr</NAME>
					</FUNCTION>
					<FUNCTION>
						<NID>0x15B6446B</NID>
						<NAME>Kernel_Library_15B6446B</NAME>
					</FUNCTION>
					<FUNCTION>
						<NID>0x5F10D406</NID>
						<NAME>sceKernelCpuResumeIntr</NAME>
					</FUNCTION>
					<FUNCTION>
						<NID>0xBEA46419</NID>
						<NAME>Kernel_Library_BEA46419</NAME>
					</FUNCTION>
				</FUNCTIONS>
			</LIBRARY>
			<LIBRARY>
				<NAME>ThreadManForUser</NAME>
				<FLAGS>0x40010011</FLAGS>
				<FUNCTIONS>
					<FUNCTION>
						<NID>0xC07BB470</NID>
						<NAME>sceKernelCreateFpl</NAME>
					</FUNCTION>
					<FUNCTION>
						<NID>0xC68D9437</NID>
						<NAME>sceKernelStartVTimer</NAME>
					</FUNCTION>
					<FUNCTION>
						<NID>0xD0AEEE87</NID>
						<NAME>sceKernelStopVTimer</NAME>
					</FUNCTION>
					<FUNCTION>
						<NID>0xD6DA4BA1</NID>
						<NAME>sceKernelCreateSema</NAME>
					</FUNCTION>
					<FUNCTION>
						<NID>0xD8B299AE</NID>
						<NAME>sceKernelSetVTimerHandler</NAME>
					</FUNCTION>
					<FUNCTION>
						<NID>0xD979E9BF</NID>
						<NAME>sceKernelAllocateFpl</NAME>
					</FUNCTION>
					<FUNCTION>
						<NID>0xE81CAF8F</NID>
						<NAME>sceKernelCreateCallback</NAME>
					</FUNCTION>
					<FUNCTION>
						<NID>0xED1410E0</NID>
						<NAME>sceKernelDeleteFpl</NAME>
					</FUNCTION>
					<FUNCTION>
						<NID>0xEDBA5844</NID>
						<NAME>sceKernelDeleteCallback</NAME>
					</FUNCTION>
					<FUNCTION>
						<NID>0xEF9E4C70</NID>
						<NAME>sceKernelDeleteEventFlag</NAME>
					</FUNCTION>
					<FUNCTION>
						<NID>0x1FB15A32</NID>
						<NAME>sceKernelSetEventFlag</NAME>
					</FUNCTION>
					<FUNCTION>
						<NID>0xF475845D</NID>
						<NAME>sceKernelStartThread</NAME>
					</FUNCTION>
					<FUNCTION>
						<NID>0xF6414A71</NID>
						<NAME>sceKernelFreeFpl</NAME>
					</FUNCTION>
					<FUNCTION>
						<NID>0x20FFF560</NID>
						<NAME>sceKernelCreateVTimer</NAME>
					</FUNCTION>
					<FUNCTION>
						<NID>0x278C0DF5</NID>
						<NAME>sceKernelWaitThreadEnd</NAME>
					</FUNCTION>
					<FUNCTION>
						<NID>0x28B6489C</NID>
						<NAME>sceKernelDeleteSema</NAME>
					</FUNCTION>
					<FUNCTION>
						<NID>0x328C546A</NID>
						<NAME>sceKernelWaitEventFlagCB</NAME>
					</FUNCTION>
					<FUNCTION>
						<NID>0x328F9E52</NID>
						<NAME>sceKernelDeleteVTimer</NAME>
					</FUNCTION>
					<FUNCTION>
						<NID>0x369ED59D</NID>
						<NAME>sceKernelGetSystemTimeLow</NAME>
					</FUNCTION>
					<FUNCTION>
						<NID>0x3F53E640</NID>
						<NAME>sceKernelSignalSema</NAME>
					</FUNCTION>
					<FUNCTION>
						<NID>0x402FCF22</NID>
						<NAME>sceKernelWaitEventFlag</NAME>
					</FUNCTION>
					<FUNCTION>
						<NID>0x446D8DE6</NID>
						<NAME>sceKernelCreateThread</NAME>
					</FUNCTION>
					<FUNCTION>
						<NID>0x4E3A1105</NID>
						<NAME>sceKernelWaitSema</NAME>
					</FUNCTION>
					<FUNCTION>
						<NID>0x55C20A00</NID>
						<NAME>sceKernelCreateEventFlag</NAME>
					</FUNCTION>
					<FUNCTION>
						<NID>0x57CF62DD</NID>
						<NAME>sceKernelGetThreadmanIdType</NAME>
					</FUNCTION>
					<FUNCTION>
						<NID>0x60107536</NID>
						<NAME>sceKernelDeleteLwMutex</NAME>
					</FUNCTION>
					<FUNCTION>
						<NID>0x110DEC9A</NID>
						<NAME>sceKernelUSec2SysClock</NAME>
					</FUNCTION>
					<FUNCTION>
						<NID>0x812346E4</NID>
						<NAME>sceKernelClearEventFlag</NAME>
					</FUNCTION>
					<FUNCTION>
						<NID>0x8FFDF9A2</NID>
						<NAME>sceKernelCancelSema</NAME>
					</FUNCTION>
					<FUNCTION>
						<NID>0x9FA03CD3</NID>
						<NAME>sceKernelDeleteThread</NAME>
					</FUNCTION>
					<FUNCTION>
						<NID>0x19CFF145</NID>
						<NAME>sceKernelCreateLwMutex</NAME>
					</FUNCTION>
				</FUNCTIONS>
			</LIBRARY>
			<LIBRARY>
				<NAME>UtilsForUser</NAME>
				<FLAGS>0x40010011</FLAGS>
				<FUNCTIONS>
					<FUNCTION>
						<NID>0xBFA98062</NID>
						<NAME>sceKernelDcacheInvalidateRange</NAME>
					</FUNCTION>
				</FUNCTIONS>
			</LIBRARY>
			<LIBRARY>
				<NAME>sceVshBridge</NAME>
				<FLAGS>0x40010011</FLAGS>
				<FUNCTIONS>
					<FUNCTION>
						<NID>0x2627CA9F</NID>
						<NAME>sceVshBridge_2627CA9F</NAME>
					</FUNCTION>
					<FUNCTION>
						<NID>0x2DED640F</NID>
						<NAME>sceVshBridge_2DED640F</NAME>
					</FUNCTION>
					<FUNCTION>
						<NID>0x38197676</NID>
						<NAME>sceVshBridge_38197676</NAME>
					</FUNCTION>
					<FUNCTION>
						<NID>0x4318A518</NID>
						<NAME>sceVshBridge_4318A518</NAME>
					</FUNCTION>
					<FUNCTION>
						<NID>0x441B0C0F</NID>
						<NAME>sceVshBridge_441B0C0F</NAME>
					</FUNCTION>
					<FUNCTION>
						<NID>0x58C7EBDA</NID>
						<NAME>sceVshBridge_58C7EBDA</NAME>
					</FUNCTION>
					<FUNCTION>
						<NID>0x6501F355</NID>
						<NAME>sceVshBridge_6501F355</NAME>
					</FUNCTION>
					<FUNCTION>
						<NID>0x888C5889</NID>
						<NAME>sceVshBridge_888C5889</NAME>
					</FUNCTION>
					<FUNCTION>
						<NID>0x8BE7B881</NID>
						<NAME>sceVshBridge_8BE7B881</NAME>
					</FUNCTION>
					<FUNCTION>
						<NID>0x8E9D28B5</NID>
						<NAME>sceVshBridge_8E9D28B5</NAME>
					</FUNCTION>
					<FUNCTION>
						<NID>0x932F1597</NID>
						<NAME>sceVshBridge_932F1597</NAME>
					</FUNCTION>
					<FUNCTION>
						<NID>0x9DDDACB8</NID>
						<NAME>sceVshBridge_9DDDACB8</NAME>
					</FUNCTION>
					<FUNCTION>
						<NID>0xA1E44C2B</NID>
						<NAME>sceVshBridge_A1E44C2B</NAME>
					</FUNCTION>
					<FUNCTION>
						<NID>0xB70D27D8</NID>
						<NAME>sceVshBridge_B70D27D8</NAME>
					</FUNCTION>
					<FUNCTION>
						<NID>0xE0F85CE4</NID>
						<NAME>sceVshBridge_E0F85CE4</NAME>
					</FUNCTION>
					<FUNCTION>
						<NID>0xFD5B0394</NID>
						<NAME>sceVshBridge_FD5B0394</NAME>
					</FUNCTION>
				</FUNCTIONS>
			</LIBRARY>
			<LIBRARY>
				<NAME>sceUsb</NAME>
				<FLAGS>0x40010011</FLAGS>
				<FUNCTIONS>
					<FUNCTION>
						<NID>0xC21645A4</NID>
						<NAME>sceUsbGetState</NAME>
					</FUNCTION>
				</FUNCTIONS>
			</LIBRARY>
			<LIBRARY>
				<NAME>sceUsbAcc</NAME>
				<FLAGS>0x40090011</FLAGS>
				<FUNCTIONS>
					<FUNCTION>
						<NID>0x79A1C743</NID>
						<NAME>sceUsbAccGetAuthStat</NAME>
					</FUNCTION>
				</FUNCTIONS>
			</LIBRARY>
			<LIBRARY>
				<NAME>sceUsb1Seg</NAME>
				<FLAGS>0x40090011</FLAGS>
				<FUNCTIONS>
					<FUNCTION>
						<NID>0x19AF6734</NID>
						<NAME>sceUsb1Seg_19AF6734</NAME>
					</FUNCTION>
					<FUNCTION>
						<NID>0x1C93552A</NID>
						<NAME>sceUsb1SegGetPacketBuffer</NAME>
					</FUNCTION>
					<FUNCTION>
						<NID>0x302D80FA</NID>
						<NAME>sceUsb1SegDestruct</NAME>
					</FUNCTION>
					<FUNCTION>
						<NID>0x41EFF237</NID>
						<NAME>sceUsb1SegGetDebug</NAME>
					</FUNCTION>
					<FUNCTION>
						<NID>0x557E6B41</NID>
						<NAME>sceUsb1Seg_557E6B41</NAME>
					</FUNCTION>
					<FUNCTION>
						<NID>0x6CC140FE</NID>
						<NAME>sceUsb1SegConstruct</NAME>
					</FUNCTION>
					<FUNCTION>
						<NID>0x8306E587</NID>
						<NAME>sceUsb1SegGetModule</NAME>
					</FUNCTION>
					<FUNCTION>
						<NID>0xD799104F</NID>
						<NAME>sceUsb1Seg_D799104F</NAME>
					</FUNCTION>
					<FUNCTION>
						<NID>0xE146560E</NID>
						<NAME>sceUsb1SegSetBPER</NAME>
					</FUNCTION>
					<FUNCTION>
						<NID>0xE2AFCC23</NID>
						<NAME>sceUsb1SegPutPacketBuffer</NAME>
					</FUNCTION>
					<FUNCTION>
						<NID>0xF8E2CEDC</NID>
						<NAME>sceUsb1SegScanCh</NAME>
					</FUNCTION>
				</FUNCTIONS>
			</LIBRARY>
		</LIBRARIES>
		</PRXFILE>
	</PRXFILES>
</PSPLIBDOC>
