<?xml version="1.0" ?>
<?xml-stylesheet type="text/xsl" href="psplibdocdisplay.xsl" ?>
<PSPLIBDOC>
	<PRXFILES>
		<PRXFILE>
		<PRX>kd/sc_sascore.prx</PRX>
		<PRXNAME>sceSAScore</PRXNAME>
		<LIBRARIES>
			<LIBRARY>
				<NAME>sceMeCore_driver</NAME>
				<FLAGS>0x00010011</FLAGS>
				<FUNCTIONS>
					<FUNCTION>
						<NID>0x3282188D</NID>
						<NAME>sceMeCore_driver_3282188D</NAME>
					</FUNCTION>
					<FUNCTION>
						<NID>0x3C96F3AC</NID>
						<NAME>sceMeCore_driver_3C96F3AC</NAME>
					</FUNCTION>
				</FUNCTIONS>
			</LIBRARY>
			<LIBRARY>
				<NAME>sceMeMemory_driver</NAME>
				<FLAGS>0x00010011</FLAGS>
				<FUNCTIONS>
					<FUNCTION>
						<NID>0x1894F4F2</NID>
						<NAME>sceMeMemory_driver_1894F4F2</NAME>
					</FUNCTION>
					<FUNCTION>
						<NID>0xBDA3A6D1</NID>
						<NAME>sceMeMemory_driver_BDA3A6D1</NAME>
					</FUNCTION>
				</FUNCTIONS>
			</LIBRARY>
			<LIBRARY>
				<NAME>UtilsForKernel</NAME>
				<FLAGS>0x00090011</FLAGS>
				<FUNCTIONS>
					<FUNCTION>
						<NID>0x34B9FA9E</NID>
						<NAME>sceKernelDcacheWritebackInvalidateRange</NAME>
					</FUNCTION>
					<FUNCTION>
						<NID>0xB435DEC5</NID>
						<NAME>sceKernelDcacheWritebackInvalidateAll</NAME>
					</FUNCTION>
					<FUNCTION>
						<NID>0xBFA98062</NID>
						<NAME>sceKernelDcacheInvalidateRange</NAME>
					</FUNCTION>
				</FUNCTIONS>
			</LIBRARY>
			<LIBRARY>
				<NAME>ThreadManForKernel</NAME>
				<FLAGS>0x00010011</FLAGS>
				<FUNCTIONS>
					<FUNCTION>
						<NID>0x28B6489C</NID>
						<NAME>sceKernelDeleteSema</NAME>
					</FUNCTION>
					<FUNCTION>
						<NID>0x3F53E640</NID>
						<NAME>sceKernelSignalSema</NAME>
					</FUNCTION>
					<FUNCTION>
						<NID>0x4E3A1105</NID>
						<NAME>sceKernelWaitSema</NAME>
					</FUNCTION>
					<FUNCTION>
						<NID>0xD6DA4BA1</NID>
						<NAME>sceKernelCreateSema</NAME>
					</FUNCTION>
				</FUNCTIONS>
			</LIBRARY>
			<LIBRARY>
				<NAME>SysMemForKernel</NAME>
				<FLAGS>0x00010011</FLAGS>
				<FUNCTIONS>
					<FUNCTION>
						<NID>0x12720EDA</NID>
						<NAME>SysMemForKernel_12720EDA</NAME>
					</FUNCTION>
				</FUNCTIONS>
			</LIBRARY>
		</LIBRARIES>
		</PRXFILE>
	</PRXFILES>
</PSPLIBDOC>
