<?xml version="1.0" ?>
<?xml-stylesheet type="text/xsl" href="psplibdocdisplay.xsl" ?>
<PSPLIBDOC>
	<PRXFILES>
		<PRXFILE>
		<PRX>kd/libasfparser.prx</PRX>
		<PRXNAME>sceASFParser</PRXNAME>
		<LIBRARIES>
			<LIBRARY>
				<NAME>sceAsfParser</NAME>
				<FLAGS>0x00010011</FLAGS>
				<FUNCTIONS>
					<FUNCTION>
						<NID>0x24DB62B1</NID>
						<NAME>sceAsfParser_24DB62B1</NAME>
					</FUNCTION>
					<FUNCTION>
						<NID>0x2CB147F7</NID>
						<NAME>sceAsfGetFrameData</NAME>
					</FUNCTION>
					<FUNCTION>
						<NID>0x320202AB</NID>
						<NAME>sceAsfParser_320202AB</NAME>
					</FUNCTION>
					<FUNCTION>
						<NID>0x3CAAC462</NID>
						<NAME>sceAsfReadData</NAME>
					</FUNCTION>
					<FUNCTION>
						<NID>0x41322F4A</NID>
						<NAME>sceAsfParser_41322F4A</NAME>
					</FUNCTION>
					<FUNCTION>
						<NID>0x685E0DA7</NID>
						<NAME>sceAsfParser_685E0DA7</NAME>
					</FUNCTION>
					<FUNCTION>
						<NID>0x6B3AE857</NID>
						<NAME>sceAsfSeekTime</NAME>
					</FUNCTION>
					<FUNCTION>
						<NID>0x6DA63281</NID>
						<NAME>sceAsfParser_6DA63281</NAME>
					</FUNCTION>
					<FUNCTION>
						<NID>0x8B08301F</NID>
						<NAME>sceAsfParserEndEntry</NAME>
					</FUNCTION>
					<FUNCTION>
						<NID>0x91B11F3A</NID>
						<NAME>sceAsfInitParser</NAME>
					</FUNCTION>
					<FUNCTION>
						<NID>0x95AD7B34</NID>
						<NAME>sceAsfCheckNeedMem</NAME>
					</FUNCTION>
					<FUNCTION>
						<NID>0xB9E4BD9E</NID>
						<NAME>sceAsfParserStartEntry</NAME>
					</FUNCTION>
					<FUNCTION>
						<NID>0xC6D98C54</NID>
						<NAME>sceAsfParser_C6D98C54</NAME>
					</FUNCTION>
				</FUNCTIONS>
			</LIBRARY>
		</LIBRARIES>
		</PRXFILE>
	</PRXFILES>
</PSPLIBDOC>
