<?xml version="1.0" ?>
<?xml-stylesheet type="text/xsl" href="psplibdocdisplay.xsl" ?>
<PSPLIBDOC>
	<PRXFILES>
		<PRXFILE>
		<PRX>kd/libdnas_core.prx</PRX>
		<PRXNAME>sceDNASCore_lib</PRXNAME>
		<LIBRARIES>
			<LIBRARY>
				<NAME>sceDNASCore_lib</NAME>
				<FLAGS>0x40090011</FLAGS>
				<FUNCTIONS>
					<FUNCTION>
						<NID>0xFA571A75</NID>
						<NAME>sceDNASCore_lib_FA571A75</NAME>
					</FUNCTION>
					<FUNCTION>
						<NID>0xBA0D27F8</NID>
						<NAME>sceDNASCore_lib_BA0D27F8</NAME>
					</FUNCTION>
					<FUNCTION>
						<NID>0xDA5939B4</NID>
						<NAME>sceDNASCore_lib_DA5939B4</NAME>
					</FUNCTION>
					<FUNCTION>
						<NID>0xC54657B7</NID>
						<NAME>sceDNASCore_lib_C54657B7</NAME>
					</FUNCTION>
					<FUNCTION>
						<NID>0x2370130E</NID>
						<NAME>sceDNASCore_lib_2370130E</NAME>
					</FUNCTION>
					<FUNCTION>
						<NID>0x4108128B</NID>
						<NAME>sceDNASCore_lib_4108128B</NAME>
					</FUNCTION>
					<FUNCTION>
						<NID>0xF0EB4367</NID>
						<NAME>sceDNASCore_lib_F0EB4367</NAME>
					</FUNCTION>
					<FUNCTION>
						<NID>0x26E1E2BD</NID>
						<NAME>sceDNASCore_lib_26E1E2BD</NAME>
					</FUNCTION>
					<FUNCTION>
						<NID>0xB6C76A14</NID>
						<NAME>sceDNASCore_lib_B6C76A14</NAME>
					</FUNCTION>
					<FUNCTION>
						<NID>0x80CEC43A</NID>
						<NAME>sceDNASCore_lib_80CEC43A</NAME>
					</FUNCTION>
					<FUNCTION>
						<NID>0x822357BB</NID>
						<NAME>sceDNASCore_lib_822357BB</NAME>
					</FUNCTION>
					<FUNCTION>
						<NID>0x8309549E</NID>
						<NAME>sceDNASCore_lib_8309549E</NAME>
					</FUNCTION>
					<FUNCTION>
						<NID>0xBA0A32CA</NID>
						<NAME>sceDNASCore_lib_BA0A32CA</NAME>
					</FUNCTION>
					<FUNCTION>
						<NID>0xD5E80301</NID>
						<NAME>sceDNASCore_lib_D5E80301</NAME>
					</FUNCTION>
					<FUNCTION>
						<NID>0x15096ECD</NID>
						<NAME>sceDNASCore_lib_15096ECD</NAME>
					</FUNCTION>
					<FUNCTION>
						<NID>0xF479F616</NID>
						<NAME>sceDNASCore_lib_F479F616</NAME>
					</FUNCTION>
					<FUNCTION>
						<NID>0x2B6C67EA</NID>
						<NAME>sceDNASCore_lib_2B6C67EA</NAME>
					</FUNCTION>
					<FUNCTION>
						<NID>0xBF6A7475</NID>
						<NAME>sceDNASCore_lib_BF6A7475</NAME>
					</FUNCTION>
				</FUNCTIONS>
			</LIBRARY>
		</LIBRARIES>
		</PRXFILE>
	</PRXFILES>
</PSPLIBDOC>
